[{"line_id":91482,"play_name":"The Tempest","speech_number":28,"line_number":"1.2.0","speaker":"GONZALO","text_entry":"SCENE II. The island. Before PROSPERO'S cell."},{"line_id":91483,"play_name":"The Tempest","speech_number":28,"line_number":"1.2.0","speaker":"GONZALO","text_entry":"Enter PROSPERO and MIRANDA"},{"line_id":91484,"play_name":"The Tempest","speech_number":1,"line_number":"1.2.1","speaker":"MIRANDA","text_entry":"If by your art, my dearest father, you have"},{"line_id":91485,"play_name":"The Tempest","speech_number":1,"line_number":"1.2.2","speaker":"MIRANDA","text_entry":"Put the wild waters in this roar, allay them."},{"line_id":91486,"play_name":"The Tempest","speech_number":1,"line_number":"1.2.3","speaker":"MIRANDA","text_entry":"The sky, it seems, would pour down stinking pitch,"},{"line_id":91487,"play_name":"The Tempest","speech_number":1,"line_number":"1.2.4","speaker":"MIRANDA","text_entry":"But that the sea, mounting to the welkin's cheek,"},{"line_id":91488,"play_name":"The Tempest","speech_number":1,"line_number":"1.2.5","speaker":"MIRANDA","text_entry":"Dashes the fire out. O, I have suffered"},{"line_id":91489,"play_name":"The Tempest","speech_number":1,"line_number":"1.2.6","speaker":"MIRANDA","text_entry":"With those that I saw suffer: a brave vessel,"},{"line_id":91490,"play_name":"The Tempest","speech_number":1,"line_number":"1.2.7","speaker":"MIRANDA","text_entry":"Who had, no doubt, some noble creature in her,"},{"line_id":91491,"play_name":"The Tempest","speech_number":1,"line_number":"1.2.8","speaker":"MIRANDA","text_entry":"Dash'd all to pieces. O, the cry did knock"},{"line_id":91492,"play_name":"The Tempest","speech_number":1,"line_number":"1.2.9","speaker":"MIRANDA","text_entry":"Against my very heart. Poor souls, they perish'd."},{"line_id":91493,"play_name":"The Tempest","speech_number":1,"line_number":"1.2.10","speaker":"MIRANDA","text_entry":"Had I been any god of power, I would"},{"line_id":91494,"play_name":"The Tempest","speech_number":1,"line_number":"1.2.11","speaker":"MIRANDA","text_entry":"Have sunk the sea within the earth or ere"},{"line_id":91495,"play_name":"The Tempest","speech_number":1,"line_number":"1.2.12","speaker":"MIRANDA","text_entry":"It should the good ship so have swallow'd and"},{"line_id":91496,"play_name":"The Tempest","speech_number":1,"line_number":"1.2.13","speaker":"MIRANDA","text_entry":"The fraughting souls within her."},{"line_id":91497,"play_name":"The Tempest","speech_number":2,"line_number":"1.2.14","speaker":"PROSPERO","text_entry":"Be collected:"},{"line_id":91498,"play_name":"The Tempest","speech_number":2,"line_number":"1.2.15","speaker":"PROSPERO","text_entry":"No more amazement: tell your piteous heart"},{"line_id":91499,"play_name":"The Tempest","speech_number":2,"line_number":"1.2.16","speaker":"PROSPERO","text_entry":"There's no harm done."},{"line_id":91500,"play_name":"The Tempest","speech_number":3,"line_number":"1.2.17","speaker":"MIRANDA","text_entry":"O, woe the day!"},{"line_id":91501,"play_name":"The Tempest","speech_number":4,"line_number":"1.2.18","speaker":"PROSPERO","text_entry":"No harm."},{"line_id":91502,"play_name":"The Tempest","speech_number":4,"line_number":"1.2.19","speaker":"PROSPERO","text_entry":"I have done nothing but in care of thee,"},{"line_id":91503,"play_name":"The Tempest","speech_number":4,"line_number":"1.2.20","speaker":"PROSPERO","text_entry":"Of thee, my dear one, thee, my daughter, who"},{"line_id":91504,"play_name":"The Tempest","speech_number":4,"line_number":"1.2.21","speaker":"PROSPERO","text_entry":"Art ignorant of what thou art, nought knowing"},{"line_id":91505,"play_name":"The Tempest","speech_number":4,"line_number":"1.2.22","speaker":"PROSPERO","text_entry":"Of whence I am, nor that I am more better"},{"line_id":91506,"play_name":"The Tempest","speech_number":4,"line_number":"1.2.23","speaker":"PROSPERO","text_entry":"Than Prospero, master of a full poor cell,"},{"line_id":91507,"play_name":"The Tempest","speech_number":4,"line_number":"1.2.24","speaker":"PROSPERO","text_entry":"And thy no greater father."},{"line_id":91508,"play_name":"The Tempest","speech_number":5,"line_number":"1.2.25","speaker":"MIRANDA","text_entry":"More to know"},{"line_id":91509,"play_name":"The Tempest","speech_number":5,"line_number":"1.2.26","speaker":"MIRANDA","text_entry":"Did never meddle with my thoughts."},{"line_id":91510,"play_name":"The Tempest","speech_number":6,"line_number":"1.2.27","speaker":"PROSPERO","text_entry":"'Tis time"},{"line_id":91511,"play_name":"The Tempest","speech_number":6,"line_number":"1.2.28","speaker":"PROSPERO","text_entry":"I should inform thee farther. Lend thy hand,"},{"line_id":91512,"play_name":"The Tempest","speech_number":6,"line_number":"1.2.29","speaker":"PROSPERO","text_entry":"And pluck my magic garment from me. So:"},{"line_id":91513,"play_name":"The Tempest","speech_number":6,"line_number":"1.2.0","speaker":"PROSPERO","text_entry":"Lays down his mantle"},{"line_id":91514,"play_name":"The Tempest","speech_number":6,"line_number":"1.2.30","speaker":"PROSPERO","text_entry":"Lie there, my art. Wipe thou thine eyes; have comfort."},{"line_id":91515,"play_name":"The Tempest","speech_number":6,"line_number":"1.2.31","speaker":"PROSPERO","text_entry":"The direful spectacle of the wreck, which touch'd"},{"line_id":91516,"play_name":"The Tempest","speech_number":6,"line_number":"1.2.32","speaker":"PROSPERO","text_entry":"The very virtue of compassion in thee,"},{"line_id":91517,"play_name":"The Tempest","speech_number":6,"line_number":"1.2.33","speaker":"PROSPERO","text_entry":"I have with such provision in mine art"},{"line_id":91518,"play_name":"The Tempest","speech_number":6,"line_number":"1.2.34","speaker":"PROSPERO","text_entry":"So safely ordered that there is no soul--"},{"line_id":91519,"play_name":"The Tempest","speech_number":6,"line_number":"1.2.35","speaker":"PROSPERO","text_entry":"No, not so much perdition as an hair"},{"line_id":91520,"play_name":"The Tempest","speech_number":6,"line_number":"1.2.36","speaker":"PROSPERO","text_entry":"Betid to any creature in the vessel"},{"line_id":91521,"play_name":"The Tempest","speech_number":6,"line_number":"1.2.37","speaker":"PROSPERO","text_entry":"Which thou heard'st cry, which thou saw'st sink. Sit down;"},{"line_id":91522,"play_name":"The Tempest","speech_number":6,"line_number":"1.2.38","speaker":"PROSPERO","text_entry":"For thou must now know farther."},{"line_id":91523,"play_name":"The Tempest","speech_number":7,"line_number":"1.2.39","speaker":"MIRANDA","text_entry":"You have often"},{"line_id":91524,"play_name":"The Tempest","speech_number":7,"line_number":"1.2.40","speaker":"MIRANDA","text_entry":"Begun to tell me what I am, but stopp'd"},{"line_id":91525,"play_name":"The Tempest","speech_number":7,"line_number":"1.2.41","speaker":"MIRANDA","text_entry":"And left me to a bootless inquisition,"},{"line_id":91526,"play_name":"The Tempest","speech_number":7,"line_number":"1.2.42","speaker":"MIRANDA","text_entry":"Concluding 'Stay: not yet.'"},{"line_id":91527,"play_name":"The Tempest","speech_number":8,"line_number":"1.2.43","speaker":"PROSPERO","text_entry":"The hour's now come;"},{"line_id":91528,"play_name":"The Tempest","speech_number":8,"line_number":"1.2.44","speaker":"PROSPERO","text_entry":"The very minute bids thee ope thine ear;"},{"line_id":91529,"play_name":"The Tempest","speech_number":8,"line_number":"1.2.45","speaker":"PROSPERO","text_entry":"Obey and be attentive. Canst thou remember"},{"line_id":91530,"play_name":"The Tempest","speech_number":8,"line_number":"1.2.46","speaker":"PROSPERO","text_entry":"A time before we came unto this cell?"},{"line_id":91531,"play_name":"The Tempest","speech_number":8,"line_number":"1.2.47","speaker":"PROSPERO","text_entry":"I do not think thou canst, for then thou wast not"},{"line_id":91532,"play_name":"The Tempest","speech_number":8,"line_number":"1.2.48","speaker":"PROSPERO","text_entry":"Out three years old."},{"line_id":91533,"play_name":"The Tempest","speech_number":9,"line_number":"1.2.49","speaker":"MIRANDA","text_entry":"Certainly, sir, I can."},{"line_id":91534,"play_name":"The Tempest","speech_number":10,"line_number":"1.2.50","speaker":"PROSPERO","text_entry":"By what? by any other house or person?"},{"line_id":91535,"play_name":"The Tempest","speech_number":10,"line_number":"1.2.51","speaker":"PROSPERO","text_entry":"Of any thing the image tell me that"},{"line_id":91536,"play_name":"The Tempest","speech_number":10,"line_number":"1.2.52","speaker":"PROSPERO","text_entry":"Hath kept with thy remembrance."},{"line_id":91537,"play_name":"The Tempest","speech_number":11,"line_number":"1.2.53","speaker":"MIRANDA","text_entry":"'Tis far off"},{"line_id":91538,"play_name":"The Tempest","speech_number":11,"line_number":"1.2.54","speaker":"MIRANDA","text_entry":"And rather like a dream than an assurance"},{"line_id":91539,"play_name":"The Tempest","speech_number":11,"line_number":"1.2.55","speaker":"MIRANDA","text_entry":"That my remembrance warrants. Had I not"},{"line_id":91540,"play_name":"The Tempest","speech_number":11,"line_number":"1.2.56","speaker":"MIRANDA","text_entry":"Four or five women once that tended me?"},{"line_id":91541,"play_name":"The Tempest","speech_number":12,"line_number":"1.2.57","speaker":"PROSPERO","text_entry":"Thou hadst, and more, Miranda. But how is it"},{"line_id":91542,"play_name":"The Tempest","speech_number":12,"line_number":"1.2.58","speaker":"PROSPERO","text_entry":"That this lives in thy mind? What seest thou else"},{"line_id":91543,"play_name":"The Tempest","speech_number":12,"line_number":"1.2.59","speaker":"PROSPERO","text_entry":"In the dark backward and abysm of time?"},{"line_id":91544,"play_name":"The Tempest","speech_number":12,"line_number":"1.2.60","speaker":"PROSPERO","text_entry":"If thou remember'st aught ere thou camest here,"},{"line_id":91545,"play_name":"The Tempest","speech_number":12,"line_number":"1.2.61","speaker":"PROSPERO","text_entry":"How thou camest here thou mayst."},{"line_id":91546,"play_name":"The Tempest","speech_number":13,"line_number":"1.2.62","speaker":"MIRANDA","text_entry":"But that I do not."},{"line_id":91547,"play_name":"The Tempest","speech_number":14,"line_number":"1.2.63","speaker":"PROSPERO","text_entry":"Twelve year since, Miranda, twelve year since,"},{"line_id":91548,"play_name":"The Tempest","speech_number":14,"line_number":"1.2.64","speaker":"PROSPERO","text_entry":"Thy father was the Duke of Milan and"},{"line_id":91549,"play_name":"The Tempest","speech_number":14,"line_number":"1.2.65","speaker":"PROSPERO","text_entry":"A prince of power."},{"line_id":91550,"play_name":"The Tempest","speech_number":15,"line_number":"1.2.66","speaker":"MIRANDA","text_entry":"Sir, are not you my father?"},{"line_id":91551,"play_name":"The Tempest","speech_number":16,"line_number":"1.2.67","speaker":"PROSPERO","text_entry":"Thy mother was a piece of virtue, and"},{"line_id":91552,"play_name":"The Tempest","speech_number":16,"line_number":"1.2.68","speaker":"PROSPERO","text_entry":"She said thou wast my daughter; and thy father"},{"line_id":91553,"play_name":"The Tempest","speech_number":16,"line_number":"1.2.69","speaker":"PROSPERO","text_entry":"Was Duke of Milan; and thou his only heir"},{"line_id":91554,"play_name":"The Tempest","speech_number":16,"line_number":"1.2.70","speaker":"PROSPERO","text_entry":"And princess no worse issued."},{"line_id":91555,"play_name":"The Tempest","speech_number":17,"line_number":"1.2.71","speaker":"MIRANDA","text_entry":"O the heavens!"},{"line_id":91556,"play_name":"The Tempest","speech_number":17,"line_number":"1.2.72","speaker":"MIRANDA","text_entry":"What foul play had we, that we came from thence?"},{"line_id":91557,"play_name":"The Tempest","speech_number":17,"line_number":"1.2.73","speaker":"MIRANDA","text_entry":"Or blessed was't we did?"},{"line_id":91558,"play_name":"The Tempest","speech_number":18,"line_number":"1.2.74","speaker":"PROSPERO","text_entry":"Both, both, my girl:"},{"line_id":91559,"play_name":"The Tempest","speech_number":18,"line_number":"1.2.75","speaker":"PROSPERO","text_entry":"By foul play, as thou say'st, were we heaved thence,"},{"line_id":91560,"play_name":"The Tempest","speech_number":18,"line_number":"1.2.76","speaker":"PROSPERO","text_entry":"But blessedly holp hither."},{"line_id":91561,"play_name":"The Tempest","speech_number":19,"line_number":"1.2.77","speaker":"MIRANDA","text_entry":"O, my heart bleeds"},{"line_id":91562,"play_name":"The Tempest","speech_number":19,"line_number":"1.2.78","speaker":"MIRANDA","text_entry":"To think o' the teen that I have turn'd you to,"},{"line_id":91563,"play_name":"The Tempest","speech_number":19,"line_number":"1.2.79","speaker":"MIRANDA","text_entry":"Which is from my remembrance! Please you, farther."},{"line_id":91564,"play_name":"The Tempest","speech_number":20,"line_number":"1.2.80","speaker":"PROSPERO","text_entry":"My brother and thy uncle, call'd Antonio--"},{"line_id":91565,"play_name":"The Tempest","speech_number":20,"line_number":"1.2.81","speaker":"PROSPERO","text_entry":"I pray thee, mark me--that a brother should"},{"line_id":91566,"play_name":"The Tempest","speech_number":20,"line_number":"1.2.82","speaker":"PROSPERO","text_entry":"Be so perfidious!--he whom next thyself"},{"line_id":91567,"play_name":"The Tempest","speech_number":20,"line_number":"1.2.83","speaker":"PROSPERO","text_entry":"Of all the world I loved and to him put"},{"line_id":91568,"play_name":"The Tempest","speech_number":20,"line_number":"1.2.84","speaker":"PROSPERO","text_entry":"The manage of my state; as at that time"},{"line_id":91569,"play_name":"The Tempest","speech_number":20,"line_number":"1.2.85","speaker":"PROSPERO","text_entry":"Through all the signories it was the first"},{"line_id":91570,"play_name":"The Tempest","speech_number":20,"line_number":"1.2.86","speaker":"PROSPERO","text_entry":"And Prospero the prime duke, being so reputed"},{"line_id":91571,"play_name":"The Tempest","speech_number":20,"line_number":"1.2.87","speaker":"PROSPERO","text_entry":"In dignity, and for the liberal arts"},{"line_id":91572,"play_name":"The Tempest","speech_number":20,"line_number":"1.2.88","speaker":"PROSPERO","text_entry":"Without a parallel; those being all my study,"},{"line_id":91573,"play_name":"The Tempest","speech_number":20,"line_number":"1.2.89","speaker":"PROSPERO","text_entry":"The government I cast upon my brother"},{"line_id":91574,"play_name":"The Tempest","speech_number":20,"line_number":"1.2.90","speaker":"PROSPERO","text_entry":"And to my state grew stranger, being transported"},{"line_id":91575,"play_name":"The Tempest","speech_number":20,"line_number":"1.2.91","speaker":"PROSPERO","text_entry":"And rapt in secret studies. Thy false uncle--"},{"line_id":91576,"play_name":"The Tempest","speech_number":20,"line_number":"1.2.92","speaker":"PROSPERO","text_entry":"Dost thou attend me?"},{"line_id":91577,"play_name":"The Tempest","speech_number":21,"line_number":"1.2.93","speaker":"MIRANDA","text_entry":"Sir, most heedfully."},{"line_id":91578,"play_name":"The Tempest","speech_number":22,"line_number":"1.2.94","speaker":"PROSPERO","text_entry":"Being once perfected how to grant suits,"},{"line_id":91579,"play_name":"The Tempest","speech_number":22,"line_number":"1.2.95","speaker":"PROSPERO","text_entry":"How to deny them, who to advance and who"},{"line_id":91580,"play_name":"The Tempest","speech_number":22,"line_number":"1.2.96","speaker":"PROSPERO","text_entry":"To trash for over-topping, new created"},{"line_id":91581,"play_name":"The Tempest","speech_number":22,"line_number":"1.2.97","speaker":"PROSPERO","text_entry":"The creatures that were mine, I say, or changed 'em,"},{"line_id":91582,"play_name":"The Tempest","speech_number":22,"line_number":"1.2.98","speaker":"PROSPERO","text_entry":"Or else new form'd 'em; having both the key"},{"line_id":91583,"play_name":"The Tempest","speech_number":22,"line_number":"1.2.99","speaker":"PROSPERO","text_entry":"Of officer and office, set all hearts i' the state"},{"line_id":91584,"play_name":"The Tempest","speech_number":22,"line_number":"1.2.100","speaker":"PROSPERO","text_entry":"To what tune pleased his ear; that now he was"},{"line_id":91585,"play_name":"The Tempest","speech_number":22,"line_number":"1.2.101","speaker":"PROSPERO","text_entry":"The ivy which had hid my princely trunk,"},{"line_id":91586,"play_name":"The Tempest","speech_number":22,"line_number":"1.2.102","speaker":"PROSPERO","text_entry":"And suck'd my verdure out on't. Thou attend'st not."},{"line_id":91587,"play_name":"The Tempest","speech_number":23,"line_number":"1.2.103","speaker":"MIRANDA","text_entry":"O, good sir, I do."},{"line_id":91588,"play_name":"The Tempest","speech_number":24,"line_number":"1.2.104","speaker":"PROSPERO","text_entry":"I pray thee, mark me."},{"line_id":91589,"play_name":"The Tempest","speech_number":24,"line_number":"1.2.105","speaker":"PROSPERO","text_entry":"I, thus neglecting worldly ends, all dedicated"},{"line_id":91590,"play_name":"The Tempest","speech_number":24,"line_number":"1.2.106","speaker":"PROSPERO","text_entry":"To closeness and the bettering of my mind"},{"line_id":91591,"play_name":"The Tempest","speech_number":24,"line_number":"1.2.107","speaker":"PROSPERO","text_entry":"With that which, but by being so retired,"},{"line_id":91592,"play_name":"The Tempest","speech_number":24,"line_number":"1.2.108","speaker":"PROSPERO","text_entry":"O'er-prized all popular rate, in my false brother"},{"line_id":91593,"play_name":"The Tempest","speech_number":24,"line_number":"1.2.109","speaker":"PROSPERO","text_entry":"Awaked an evil nature; and my trust,"},{"line_id":91594,"play_name":"The Tempest","speech_number":24,"line_number":"1.2.110","speaker":"PROSPERO","text_entry":"Like a good parent, did beget of him"},{"line_id":91595,"play_name":"The Tempest","speech_number":24,"line_number":"1.2.111","speaker":"PROSPERO","text_entry":"A falsehood in its contrary as great"},{"line_id":91596,"play_name":"The Tempest","speech_number":24,"line_number":"1.2.112","speaker":"PROSPERO","text_entry":"As my trust was; which had indeed no limit,"},{"line_id":91597,"play_name":"The Tempest","speech_number":24,"line_number":"1.2.113","speaker":"PROSPERO","text_entry":"A confidence sans bound. He being thus lorded,"},{"line_id":91598,"play_name":"The Tempest","speech_number":24,"line_number":"1.2.114","speaker":"PROSPERO","text_entry":"Not only with what my revenue yielded,"},{"line_id":91599,"play_name":"The Tempest","speech_number":24,"line_number":"1.2.115","speaker":"PROSPERO","text_entry":"But what my power might else exact, like one"},{"line_id":91600,"play_name":"The Tempest","speech_number":24,"line_number":"1.2.116","speaker":"PROSPERO","text_entry":"Who having into truth, by telling of it,"},{"line_id":91601,"play_name":"The Tempest","speech_number":24,"line_number":"1.2.117","speaker":"PROSPERO","text_entry":"Made such a sinner of his memory,"},{"line_id":91602,"play_name":"The Tempest","speech_number":24,"line_number":"1.2.118","speaker":"PROSPERO","text_entry":"To credit his own lie, he did believe"},{"line_id":91603,"play_name":"The Tempest","speech_number":24,"line_number":"1.2.119","speaker":"PROSPERO","text_entry":"He was indeed the duke; out o' the substitution"},{"line_id":91604,"play_name":"The Tempest","speech_number":24,"line_number":"1.2.120","speaker":"PROSPERO","text_entry":"And executing the outward face of royalty,"},{"line_id":91605,"play_name":"The Tempest","speech_number":24,"line_number":"1.2.121","speaker":"PROSPERO","text_entry":"With all prerogative: hence his ambition growing--"},{"line_id":91606,"play_name":"The Tempest","speech_number":24,"line_number":"1.2.122","speaker":"PROSPERO","text_entry":"Dost thou hear?"},{"line_id":91607,"play_name":"The Tempest","speech_number":25,"line_number":"1.2.123","speaker":"MIRANDA","text_entry":"Your tale, sir, would cure deafness."},{"line_id":91608,"play_name":"The Tempest","speech_number":26,"line_number":"1.2.124","speaker":"PROSPERO","text_entry":"To have no screen between this part he play'd"},{"line_id":91609,"play_name":"The Tempest","speech_number":26,"line_number":"1.2.125","speaker":"PROSPERO","text_entry":"And him he play'd it for, he needs will be"},{"line_id":91610,"play_name":"The Tempest","speech_number":26,"line_number":"1.2.126","speaker":"PROSPERO","text_entry":"Absolute Milan. Me, poor man, my library"},{"line_id":91611,"play_name":"The Tempest","speech_number":26,"line_number":"1.2.127","speaker":"PROSPERO","text_entry":"Was dukedom large enough: of temporal royalties"},{"line_id":91612,"play_name":"The Tempest","speech_number":26,"line_number":"1.2.128","speaker":"PROSPERO","text_entry":"He thinks me now incapable; confederates--"},{"line_id":91613,"play_name":"The Tempest","speech_number":26,"line_number":"1.2.129","speaker":"PROSPERO","text_entry":"So dry he was for sway--wi' the King of Naples"},{"line_id":91614,"play_name":"The Tempest","speech_number":26,"line_number":"1.2.130","speaker":"PROSPERO","text_entry":"To give him annual tribute, do him homage,"},{"line_id":91615,"play_name":"The Tempest","speech_number":26,"line_number":"1.2.131","speaker":"PROSPERO","text_entry":"Subject his coronet to his crown and bend"},{"line_id":91616,"play_name":"The Tempest","speech_number":26,"line_number":"1.2.132","speaker":"PROSPERO","text_entry":"The dukedom yet unbow'd--alas, poor Milan!--"},{"line_id":91617,"play_name":"The Tempest","speech_number":26,"line_number":"1.2.133","speaker":"PROSPERO","text_entry":"To most ignoble stooping."},{"line_id":91618,"play_name":"The Tempest","speech_number":27,"line_number":"1.2.134","speaker":"MIRANDA","text_entry":"O the heavens!"},{"line_id":91619,"play_name":"The Tempest","speech_number":28,"line_number":"1.2.135","speaker":"PROSPERO","text_entry":"Mark his condition and the event; then tell me"},{"line_id":91620,"play_name":"The Tempest","speech_number":28,"line_number":"1.2.136","speaker":"PROSPERO","text_entry":"If this might be a brother."},{"line_id":91621,"play_name":"The Tempest","speech_number":29,"line_number":"1.2.137","speaker":"MIRANDA","text_entry":"I should sin"},{"line_id":91622,"play_name":"The Tempest","speech_number":29,"line_number":"1.2.138","speaker":"MIRANDA","text_entry":"To think but nobly of my grandmother:"},{"line_id":91623,"play_name":"The Tempest","speech_number":29,"line_number":"1.2.139","speaker":"MIRANDA","text_entry":"Good wombs have borne bad sons."},{"line_id":91624,"play_name":"The Tempest","speech_number":30,"line_number":"1.2.140","speaker":"PROSPERO","text_entry":"Now the condition."},{"line_id":91625,"play_name":"The Tempest","speech_number":30,"line_number":"1.2.141","speaker":"PROSPERO","text_entry":"The King of Naples, being an enemy"},{"line_id":91626,"play_name":"The Tempest","speech_number":30,"line_number":"1.2.142","speaker":"PROSPERO","text_entry":"To me inveterate, hearkens my brother's suit;"},{"line_id":91627,"play_name":"The Tempest","speech_number":30,"line_number":"1.2.143","speaker":"PROSPERO","text_entry":"Which was, that he, in lieu o' the premises"},{"line_id":91628,"play_name":"The Tempest","speech_number":30,"line_number":"1.2.144","speaker":"PROSPERO","text_entry":"Of homage and I know not how much tribute,"},{"line_id":91629,"play_name":"The Tempest","speech_number":30,"line_number":"1.2.145","speaker":"PROSPERO","text_entry":"Should presently extirpate me and mine"},{"line_id":91630,"play_name":"The Tempest","speech_number":30,"line_number":"1.2.146","speaker":"PROSPERO","text_entry":"Out of the dukedom and confer fair Milan"},{"line_id":91631,"play_name":"The Tempest","speech_number":30,"line_number":"1.2.147","speaker":"PROSPERO","text_entry":"With all the honours on my brother: whereon,"},{"line_id":91632,"play_name":"The Tempest","speech_number":30,"line_number":"1.2.148","speaker":"PROSPERO","text_entry":"A treacherous army levied, one midnight"},{"line_id":91633,"play_name":"The Tempest","speech_number":30,"line_number":"1.2.149","speaker":"PROSPERO","text_entry":"Fated to the purpose did Antonio open"},{"line_id":91634,"play_name":"The Tempest","speech_number":30,"line_number":"1.2.150","speaker":"PROSPERO","text_entry":"The gates of Milan, and, i' the dead of darkness,"},{"line_id":91635,"play_name":"The Tempest","speech_number":30,"line_number":"1.2.151","speaker":"PROSPERO","text_entry":"The ministers for the purpose hurried thence"},{"line_id":91636,"play_name":"The Tempest","speech_number":30,"line_number":"1.2.152","speaker":"PROSPERO","text_entry":"Me and thy crying self."},{"line_id":91637,"play_name":"The Tempest","speech_number":31,"line_number":"1.2.153","speaker":"MIRANDA","text_entry":"Alack, for pity!"},{"line_id":91638,"play_name":"The Tempest","speech_number":31,"line_number":"1.2.154","speaker":"MIRANDA","text_entry":"I, not remembering how I cried out then,"},{"line_id":91639,"play_name":"The Tempest","speech_number":31,"line_number":"1.2.155","speaker":"MIRANDA","text_entry":"Will cry it o'er again: it is a hint"},{"line_id":91640,"play_name":"The Tempest","speech_number":31,"line_number":"1.2.156","speaker":"MIRANDA","text_entry":"That wrings mine eyes to't."},{"line_id":91641,"play_name":"The Tempest","speech_number":32,"line_number":"1.2.157","speaker":"PROSPERO","text_entry":"Hear a little further"},{"line_id":91642,"play_name":"The Tempest","speech_number":32,"line_number":"1.2.158","speaker":"PROSPERO","text_entry":"And then I'll bring thee to the present business"},{"line_id":91643,"play_name":"The Tempest","speech_number":32,"line_number":"1.2.159","speaker":"PROSPERO","text_entry":"Which now's upon's; without the which this story"},{"line_id":91644,"play_name":"The Tempest","speech_number":32,"line_number":"1.2.160","speaker":"PROSPERO","text_entry":"Were most impertinent."},{"line_id":91645,"play_name":"The Tempest","speech_number":33,"line_number":"1.2.161","speaker":"MIRANDA","text_entry":"Wherefore did they not"},{"line_id":91646,"play_name":"The Tempest","speech_number":33,"line_number":"1.2.162","speaker":"MIRANDA","text_entry":"That hour destroy us?"},{"line_id":91647,"play_name":"The Tempest","speech_number":34,"line_number":"1.2.163","speaker":"PROSPERO","text_entry":"Well demanded, wench:"},{"line_id":91648,"play_name":"The Tempest","speech_number":34,"line_number":"1.2.164","speaker":"PROSPERO","text_entry":"My tale provokes that question. Dear, they durst not,"},{"line_id":91649,"play_name":"The Tempest","speech_number":34,"line_number":"1.2.165","speaker":"PROSPERO","text_entry":"So dear the love my people bore me, nor set"},{"line_id":91650,"play_name":"The Tempest","speech_number":34,"line_number":"1.2.166","speaker":"PROSPERO","text_entry":"A mark so bloody on the business, but"},{"line_id":91651,"play_name":"The Tempest","speech_number":34,"line_number":"1.2.167","speaker":"PROSPERO","text_entry":"With colours fairer painted their foul ends."},{"line_id":91652,"play_name":"The Tempest","speech_number":34,"line_number":"1.2.168","speaker":"PROSPERO","text_entry":"In few, they hurried us aboard a bark,"},{"line_id":91653,"play_name":"The Tempest","speech_number":34,"line_number":"1.2.169","speaker":"PROSPERO","text_entry":"Bore us some leagues to sea; where they prepared"},{"line_id":91654,"play_name":"The Tempest","speech_number":34,"line_number":"1.2.170","speaker":"PROSPERO","text_entry":"A rotten carcass of a boat, not rigg'd,"},{"line_id":91655,"play_name":"The Tempest","speech_number":34,"line_number":"1.2.171","speaker":"PROSPERO","text_entry":"Nor tackle, sail, nor mast; the very rats"},{"line_id":91656,"play_name":"The Tempest","speech_number":34,"line_number":"1.2.172","speaker":"PROSPERO","text_entry":"Instinctively had quit it: there they hoist us,"},{"line_id":91657,"play_name":"The Tempest","speech_number":34,"line_number":"1.2.173","speaker":"PROSPERO","text_entry":"To cry to the sea that roar'd to us, to sigh"},{"line_id":91658,"play_name":"The Tempest","speech_number":34,"line_number":"1.2.174","speaker":"PROSPERO","text_entry":"To the winds whose pity, sighing back again,"},{"line_id":91659,"play_name":"The Tempest","speech_number":34,"line_number":"1.2.175","speaker":"PROSPERO","text_entry":"Did us but loving wrong."},{"line_id":91660,"play_name":"The Tempest","speech_number":35,"line_number":"1.2.176","speaker":"MIRANDA","text_entry":"Alack, what trouble"},{"line_id":91661,"play_name":"The Tempest","speech_number":35,"line_number":"1.2.177","speaker":"MIRANDA","text_entry":"Was I then to you!"},{"line_id":91662,"play_name":"The Tempest","speech_number":36,"line_number":"1.2.178","speaker":"PROSPERO","text_entry":"O, a cherubim"},{"line_id":91663,"play_name":"The Tempest","speech_number":36,"line_number":"1.2.179","speaker":"PROSPERO","text_entry":"Thou wast that did preserve me. Thou didst smile."},{"line_id":91664,"play_name":"The Tempest","speech_number":36,"line_number":"1.2.180","speaker":"PROSPERO","text_entry":"Infused with a fortitude from heaven,"},{"line_id":91665,"play_name":"The Tempest","speech_number":36,"line_number":"1.2.181","speaker":"PROSPERO","text_entry":"When I have deck'd the sea with drops full salt,"},{"line_id":91666,"play_name":"The Tempest","speech_number":36,"line_number":"1.2.182","speaker":"PROSPERO","text_entry":"Under my burthen groan'd; which raised in me"},{"line_id":91667,"play_name":"The Tempest","speech_number":36,"line_number":"1.2.183","speaker":"PROSPERO","text_entry":"An undergoing stomach, to bear up"},{"line_id":91668,"play_name":"The Tempest","speech_number":36,"line_number":"1.2.184","speaker":"PROSPERO","text_entry":"Against what should ensue."},{"line_id":91669,"play_name":"The Tempest","speech_number":37,"line_number":"1.2.185","speaker":"MIRANDA","text_entry":"How came we ashore?"},{"line_id":91670,"play_name":"The Tempest","speech_number":38,"line_number":"1.2.186","speaker":"PROSPERO","text_entry":"By Providence divine."},{"line_id":91671,"play_name":"The Tempest","speech_number":38,"line_number":"1.2.187","speaker":"PROSPERO","text_entry":"Some food we had and some fresh water that"},{"line_id":91672,"play_name":"The Tempest","speech_number":38,"line_number":"1.2.188","speaker":"PROSPERO","text_entry":"A noble Neapolitan, Gonzalo,"},{"line_id":91673,"play_name":"The Tempest","speech_number":38,"line_number":"1.2.189","speaker":"PROSPERO","text_entry":"Out of his charity, being then appointed"},{"line_id":91674,"play_name":"The Tempest","speech_number":38,"line_number":"1.2.190","speaker":"PROSPERO","text_entry":"Master of this design, did give us, with"},{"line_id":91675,"play_name":"The Tempest","speech_number":38,"line_number":"1.2.191","speaker":"PROSPERO","text_entry":"Rich garments, linens, stuffs and necessaries,"},{"line_id":91676,"play_name":"The Tempest","speech_number":38,"line_number":"1.2.192","speaker":"PROSPERO","text_entry":"Which since have steaded much; so, of his gentleness,"},{"line_id":91677,"play_name":"The Tempest","speech_number":38,"line_number":"1.2.193","speaker":"PROSPERO","text_entry":"Knowing I loved my books, he furnish'd me"},{"line_id":91678,"play_name":"The Tempest","speech_number":38,"line_number":"1.2.194","speaker":"PROSPERO","text_entry":"From mine own library with volumes that"},{"line_id":91679,"play_name":"The Tempest","speech_number":38,"line_number":"1.2.195","speaker":"PROSPERO","text_entry":"I prize above my dukedom."},{"line_id":91680,"play_name":"The Tempest","speech_number":39,"line_number":"1.2.196","speaker":"MIRANDA","text_entry":"Would I might"},{"line_id":91681,"play_name":"The Tempest","speech_number":39,"line_number":"1.2.197","speaker":"MIRANDA","text_entry":"But ever see that man!"},{"line_id":91682,"play_name":"The Tempest","speech_number":40,"line_number":"1.2.198","speaker":"PROSPERO","text_entry":"Now I arise:"},{"line_id":91683,"play_name":"The Tempest","speech_number":40,"line_number":"1.2.0","speaker":"PROSPERO","text_entry":"Resumes his mantle"},{"line_id":91684,"play_name":"The Tempest","speech_number":40,"line_number":"1.2.199","speaker":"PROSPERO","text_entry":"Sit still, and hear the last of our sea-sorrow."},{"line_id":91685,"play_name":"The Tempest","speech_number":40,"line_number":"1.2.200","speaker":"PROSPERO","text_entry":"Here in this island we arrived; and here"},{"line_id":91686,"play_name":"The Tempest","speech_number":40,"line_number":"1.2.201","speaker":"PROSPERO","text_entry":"Have I, thy schoolmaster, made thee more profit"},{"line_id":91687,"play_name":"The Tempest","speech_number":40,"line_number":"1.2.202","speaker":"PROSPERO","text_entry":"Than other princesses can that have more time"},{"line_id":91688,"play_name":"The Tempest","speech_number":40,"line_number":"1.2.203","speaker":"PROSPERO","text_entry":"For vainer hours and tutors not so careful."},{"line_id":91689,"play_name":"The Tempest","speech_number":41,"line_number":"1.2.204","speaker":"MIRANDA","text_entry":"Heavens thank you for't! And now, I pray you, sir,"},{"line_id":91690,"play_name":"The Tempest","speech_number":41,"line_number":"1.2.205","speaker":"MIRANDA","text_entry":"For still 'tis beating in my mind, your reason"},{"line_id":91691,"play_name":"The Tempest","speech_number":41,"line_number":"1.2.206","speaker":"MIRANDA","text_entry":"For raising this sea-storm?"},{"line_id":91692,"play_name":"The Tempest","speech_number":42,"line_number":"1.2.207","speaker":"PROSPERO","text_entry":"Know thus far forth."},{"line_id":91693,"play_name":"The Tempest","speech_number":42,"line_number":"1.2.208","speaker":"PROSPERO","text_entry":"By accident most strange, bountiful Fortune,"},{"line_id":91694,"play_name":"The Tempest","speech_number":42,"line_number":"1.2.209","speaker":"PROSPERO","text_entry":"Now my dear lady, hath mine enemies"},{"line_id":91695,"play_name":"The Tempest","speech_number":42,"line_number":"1.2.210","speaker":"PROSPERO","text_entry":"Brought to this shore; and by my prescience"},{"line_id":91696,"play_name":"The Tempest","speech_number":42,"line_number":"1.2.211","speaker":"PROSPERO","text_entry":"I find my zenith doth depend upon"},{"line_id":91697,"play_name":"The Tempest","speech_number":42,"line_number":"1.2.212","speaker":"PROSPERO","text_entry":"A most auspicious star, whose influence"},{"line_id":91698,"play_name":"The Tempest","speech_number":42,"line_number":"1.2.213","speaker":"PROSPERO","text_entry":"If now I court not but omit, my fortunes"},{"line_id":91699,"play_name":"The Tempest","speech_number":42,"line_number":"1.2.214","speaker":"PROSPERO","text_entry":"Will ever after droop. Here cease more questions:"},{"line_id":91700,"play_name":"The Tempest","speech_number":42,"line_number":"1.2.215","speaker":"PROSPERO","text_entry":"Thou art inclined to sleep; 'tis a good dulness,"},{"line_id":91701,"play_name":"The Tempest","speech_number":42,"line_number":"1.2.216","speaker":"PROSPERO","text_entry":"And give it way: I know thou canst not choose."},{"line_id":91702,"play_name":"The Tempest","speech_number":42,"line_number":"1.2.0","speaker":"PROSPERO","text_entry":"MIRANDA sleeps"},{"line_id":91703,"play_name":"The Tempest","speech_number":42,"line_number":"1.2.217","speaker":"PROSPERO","text_entry":"Come away, servant, come. I am ready now."},{"line_id":91704,"play_name":"The Tempest","speech_number":42,"line_number":"1.2.218","speaker":"PROSPERO","text_entry":"Approach, my Ariel, come."},{"line_id":91705,"play_name":"The Tempest","speech_number":42,"line_number":"1.2.0","speaker":"PROSPERO","text_entry":"Enter ARIEL"},{"line_id":91706,"play_name":"The Tempest","speech_number":43,"line_number":"1.2.219","speaker":"ARIEL","text_entry":"All hail, great master! grave sir, hail! I come"},{"line_id":91707,"play_name":"The Tempest","speech_number":43,"line_number":"1.2.220","speaker":"ARIEL","text_entry":"To answer thy best pleasure; be't to fly,"},{"line_id":91708,"play_name":"The Tempest","speech_number":43,"line_number":"1.2.221","speaker":"ARIEL","text_entry":"To swim, to dive into the fire, to ride"},{"line_id":91709,"play_name":"The Tempest","speech_number":43,"line_number":"1.2.222","speaker":"ARIEL","text_entry":"On the curl'd clouds, to thy strong bidding task"},{"line_id":91710,"play_name":"The Tempest","speech_number":43,"line_number":"1.2.223","speaker":"ARIEL","text_entry":"Ariel and all his quality."},{"line_id":91711,"play_name":"The Tempest","speech_number":44,"line_number":"1.2.224","speaker":"PROSPERO","text_entry":"Hast thou, spirit,"},{"line_id":91712,"play_name":"The Tempest","speech_number":44,"line_number":"1.2.225","speaker":"PROSPERO","text_entry":"Perform'd to point the tempest that I bade thee?"},{"line_id":91713,"play_name":"The Tempest","speech_number":45,"line_number":"1.2.226","speaker":"ARIEL","text_entry":"To every article."},{"line_id":91714,"play_name":"The Tempest","speech_number":45,"line_number":"1.2.227","speaker":"ARIEL","text_entry":"I boarded the king's ship; now on the beak,"},{"line_id":91715,"play_name":"The Tempest","speech_number":45,"line_number":"1.2.228","speaker":"ARIEL","text_entry":"Now in the waist, the deck, in every cabin,"},{"line_id":91716,"play_name":"The Tempest","speech_number":45,"line_number":"1.2.229","speaker":"ARIEL","text_entry":"I flamed amazement: sometime I'ld divide,"},{"line_id":91717,"play_name":"The Tempest","speech_number":45,"line_number":"1.2.230","speaker":"ARIEL","text_entry":"And burn in many places; on the topmast,"},{"line_id":91718,"play_name":"The Tempest","speech_number":45,"line_number":"1.2.231","speaker":"ARIEL","text_entry":"The yards and bowsprit, would I flame distinctly,"},{"line_id":91719,"play_name":"The Tempest","speech_number":45,"line_number":"1.2.232","speaker":"ARIEL","text_entry":"Then meet and join. Jove's lightnings, the precursors"},{"line_id":91720,"play_name":"The Tempest","speech_number":45,"line_number":"1.2.233","speaker":"ARIEL","text_entry":"O' the dreadful thunder-claps, more momentary"},{"line_id":91721,"play_name":"The Tempest","speech_number":45,"line_number":"1.2.234","speaker":"ARIEL","text_entry":"And sight-outrunning were not; the fire and cracks"},{"line_id":91722,"play_name":"The Tempest","speech_number":45,"line_number":"1.2.235","speaker":"ARIEL","text_entry":"Of sulphurous roaring the most mighty Neptune"},{"line_id":91723,"play_name":"The Tempest","speech_number":45,"line_number":"1.2.236","speaker":"ARIEL","text_entry":"Seem to besiege and make his bold waves tremble,"},{"line_id":91724,"play_name":"The Tempest","speech_number":45,"line_number":"1.2.237","speaker":"ARIEL","text_entry":"Yea, his dread trident shake."},{"line_id":91725,"play_name":"The Tempest","speech_number":46,"line_number":"1.2.238","speaker":"PROSPERO","text_entry":"My brave spirit!"},{"line_id":91726,"play_name":"The Tempest","speech_number":46,"line_number":"1.2.239","speaker":"PROSPERO","text_entry":"Who was so firm, so constant, that this coil"},{"line_id":91727,"play_name":"The Tempest","speech_number":46,"line_number":"1.2.240","speaker":"PROSPERO","text_entry":"Would not infect his reason?"},{"line_id":91728,"play_name":"The Tempest","speech_number":47,"line_number":"1.2.241","speaker":"ARIEL","text_entry":"Not a soul"},{"line_id":91729,"play_name":"The Tempest","speech_number":47,"line_number":"1.2.242","speaker":"ARIEL","text_entry":"But felt a fever of the mad and play'd"},{"line_id":91730,"play_name":"The Tempest","speech_number":47,"line_number":"1.2.243","speaker":"ARIEL","text_entry":"Some tricks of desperation. All but mariners"},{"line_id":91731,"play_name":"The Tempest","speech_number":47,"line_number":"1.2.244","speaker":"ARIEL","text_entry":"Plunged in the foaming brine and quit the vessel,"},{"line_id":91732,"play_name":"The Tempest","speech_number":47,"line_number":"1.2.245","speaker":"ARIEL","text_entry":"Then all afire with me: the king's son, Ferdinand,"},{"line_id":91733,"play_name":"The Tempest","speech_number":47,"line_number":"1.2.246","speaker":"ARIEL","text_entry":"With hair up-staring,--then like reeds, not hair,--"},{"line_id":91734,"play_name":"The Tempest","speech_number":47,"line_number":"1.2.247","speaker":"ARIEL","text_entry":"Was the first man that leap'd; cried, 'Hell is empty"},{"line_id":91735,"play_name":"The Tempest","speech_number":47,"line_number":"1.2.248","speaker":"ARIEL","text_entry":"And all the devils are here.'"},{"line_id":91736,"play_name":"The Tempest","speech_number":48,"line_number":"1.2.249","speaker":"PROSPERO","text_entry":"Why that's my spirit!"},{"line_id":91737,"play_name":"The Tempest","speech_number":48,"line_number":"1.2.250","speaker":"PROSPERO","text_entry":"But was not this nigh shore?"},{"line_id":91738,"play_name":"The Tempest","speech_number":49,"line_number":"1.2.251","speaker":"ARIEL","text_entry":"Close by, my master."},{"line_id":91739,"play_name":"The Tempest","speech_number":50,"line_number":"1.2.252","speaker":"PROSPERO","text_entry":"But are they, Ariel, safe?"},{"line_id":91740,"play_name":"The Tempest","speech_number":51,"line_number":"1.2.253","speaker":"ARIEL","text_entry":"Not a hair perish'd;"},{"line_id":91741,"play_name":"The Tempest","speech_number":51,"line_number":"1.2.254","speaker":"ARIEL","text_entry":"On their sustaining garments not a blemish,"},{"line_id":91742,"play_name":"The Tempest","speech_number":51,"line_number":"1.2.255","speaker":"ARIEL","text_entry":"But fresher than before: and, as thou badest me,"},{"line_id":91743,"play_name":"The Tempest","speech_number":51,"line_number":"1.2.256","speaker":"ARIEL","text_entry":"In troops I have dispersed them 'bout the isle."},{"line_id":91744,"play_name":"The Tempest","speech_number":51,"line_number":"1.2.257","speaker":"ARIEL","text_entry":"The king's son have I landed by himself;"},{"line_id":91745,"play_name":"The Tempest","speech_number":51,"line_number":"1.2.258","speaker":"ARIEL","text_entry":"Whom I left cooling of the air with sighs"},{"line_id":91746,"play_name":"The Tempest","speech_number":51,"line_number":"1.2.259","speaker":"ARIEL","text_entry":"In an odd angle of the isle and sitting,"},{"line_id":91747,"play_name":"The Tempest","speech_number":51,"line_number":"1.2.260","speaker":"ARIEL","text_entry":"His arms in this sad knot."},{"line_id":91748,"play_name":"The Tempest","speech_number":52,"line_number":"1.2.261","speaker":"PROSPERO","text_entry":"Of the king's ship"},{"line_id":91749,"play_name":"The Tempest","speech_number":52,"line_number":"1.2.262","speaker":"PROSPERO","text_entry":"The mariners say how thou hast disposed"},{"line_id":91750,"play_name":"The Tempest","speech_number":52,"line_number":"1.2.263","speaker":"PROSPERO","text_entry":"And all the rest o' the fleet."},{"line_id":91751,"play_name":"The Tempest","speech_number":53,"line_number":"1.2.264","speaker":"ARIEL","text_entry":"Safely in harbour"},{"line_id":91752,"play_name":"The Tempest","speech_number":53,"line_number":"1.2.265","speaker":"ARIEL","text_entry":"Is the king's ship; in the deep nook, where once"},{"line_id":91753,"play_name":"The Tempest","speech_number":53,"line_number":"1.2.266","speaker":"ARIEL","text_entry":"Thou call'dst me up at midnight to fetch dew"},{"line_id":91754,"play_name":"The Tempest","speech_number":53,"line_number":"1.2.267","speaker":"ARIEL","text_entry":"From the still-vex'd Bermoothes, there she's hid:"},{"line_id":91755,"play_name":"The Tempest","speech_number":53,"line_number":"1.2.268","speaker":"ARIEL","text_entry":"The mariners all under hatches stow'd;"},{"line_id":91756,"play_name":"The Tempest","speech_number":53,"line_number":"1.2.269","speaker":"ARIEL","text_entry":"Who, with a charm join'd to their suffer'd labour,"},{"line_id":91757,"play_name":"The Tempest","speech_number":53,"line_number":"1.2.270","speaker":"ARIEL","text_entry":"I have left asleep; and for the rest o' the fleet"},{"line_id":91758,"play_name":"The Tempest","speech_number":53,"line_number":"1.2.271","speaker":"ARIEL","text_entry":"Which I dispersed, they all have met again"},{"line_id":91759,"play_name":"The Tempest","speech_number":53,"line_number":"1.2.272","speaker":"ARIEL","text_entry":"And are upon the Mediterranean flote,"},{"line_id":91760,"play_name":"The Tempest","speech_number":53,"line_number":"1.2.273","speaker":"ARIEL","text_entry":"Bound sadly home for Naples,"},{"line_id":91761,"play_name":"The Tempest","speech_number":53,"line_number":"1.2.274","speaker":"ARIEL","text_entry":"Supposing that they saw the king's ship wreck'd"},{"line_id":91762,"play_name":"The Tempest","speech_number":53,"line_number":"1.2.275","speaker":"ARIEL","text_entry":"And his great person perish."},{"line_id":91763,"play_name":"The Tempest","speech_number":54,"line_number":"1.2.276","speaker":"PROSPERO","text_entry":"Ariel, thy charge"},{"line_id":91764,"play_name":"The Tempest","speech_number":54,"line_number":"1.2.277","speaker":"PROSPERO","text_entry":"Exactly is perform'd: but there's more work."},{"line_id":91765,"play_name":"The Tempest","speech_number":54,"line_number":"1.2.278","speaker":"PROSPERO","text_entry":"What is the time o' the day?"},{"line_id":91766,"play_name":"The Tempest","speech_number":55,"line_number":"1.2.279","speaker":"ARIEL","text_entry":"Past the mid season."},{"line_id":91767,"play_name":"The Tempest","speech_number":56,"line_number":"1.2.280","speaker":"PROSPERO","text_entry":"At least two glasses. The time 'twixt six and now"},{"line_id":91768,"play_name":"The Tempest","speech_number":56,"line_number":"1.2.281","speaker":"PROSPERO","text_entry":"Must by us both be spent most preciously."},{"line_id":91769,"play_name":"The Tempest","speech_number":57,"line_number":"1.2.282","speaker":"ARIEL","text_entry":"Is there more toil? Since thou dost give me pains,"},{"line_id":91770,"play_name":"The Tempest","speech_number":57,"line_number":"1.2.283","speaker":"ARIEL","text_entry":"Let me remember thee what thou hast promised,"},{"line_id":91771,"play_name":"The Tempest","speech_number":57,"line_number":"1.2.284","speaker":"ARIEL","text_entry":"Which is not yet perform'd me."},{"line_id":91772,"play_name":"The Tempest","speech_number":58,"line_number":"1.2.285","speaker":"PROSPERO","text_entry":"How now? moody?"},{"line_id":91773,"play_name":"The Tempest","speech_number":58,"line_number":"1.2.286","speaker":"PROSPERO","text_entry":"What is't thou canst demand?"},{"line_id":91774,"play_name":"The Tempest","speech_number":59,"line_number":"1.2.287","speaker":"ARIEL","text_entry":"My liberty."},{"line_id":91775,"play_name":"The Tempest","speech_number":60,"line_number":"1.2.288","speaker":"PROSPERO","text_entry":"Before the time be out? no more!"},{"line_id":91776,"play_name":"The Tempest","speech_number":61,"line_number":"1.2.289","speaker":"ARIEL","text_entry":"I prithee,"},{"line_id":91777,"play_name":"The Tempest","speech_number":61,"line_number":"1.2.290","speaker":"ARIEL","text_entry":"Remember I have done thee worthy service;"},{"line_id":91778,"play_name":"The Tempest","speech_number":61,"line_number":"1.2.291","speaker":"ARIEL","text_entry":"Told thee no lies, made thee no mistakings, served"},{"line_id":91779,"play_name":"The Tempest","speech_number":61,"line_number":"1.2.292","speaker":"ARIEL","text_entry":"Without or grudge or grumblings: thou didst promise"},{"line_id":91780,"play_name":"The Tempest","speech_number":61,"line_number":"1.2.293","speaker":"ARIEL","text_entry":"To bate me a full year."},{"line_id":91781,"play_name":"The Tempest","speech_number":62,"line_number":"1.2.294","speaker":"PROSPERO","text_entry":"Dost thou forget"},{"line_id":91782,"play_name":"The Tempest","speech_number":62,"line_number":"1.2.295","speaker":"PROSPERO","text_entry":"From what a torment I did free thee?"},{"line_id":91783,"play_name":"The Tempest","speech_number":63,"line_number":"1.2.296","speaker":"ARIEL","text_entry":"No."},{"line_id":91784,"play_name":"The Tempest","speech_number":64,"line_number":"1.2.297","speaker":"PROSPERO","text_entry":"Thou dost, and think'st it much to tread the ooze"},{"line_id":91785,"play_name":"The Tempest","speech_number":64,"line_number":"1.2.298","speaker":"PROSPERO","text_entry":"Of the salt deep,"},{"line_id":91786,"play_name":"The Tempest","speech_number":64,"line_number":"1.2.299","speaker":"PROSPERO","text_entry":"To run upon the sharp wind of the north,"},{"line_id":91787,"play_name":"The Tempest","speech_number":64,"line_number":"1.2.300","speaker":"PROSPERO","text_entry":"To do me business in the veins o' the earth"},{"line_id":91788,"play_name":"The Tempest","speech_number":64,"line_number":"1.2.301","speaker":"PROSPERO","text_entry":"When it is baked with frost."},{"line_id":91789,"play_name":"The Tempest","speech_number":65,"line_number":"1.2.302","speaker":"ARIEL","text_entry":"I do not, sir."},{"line_id":91790,"play_name":"The Tempest","speech_number":66,"line_number":"1.2.303","speaker":"PROSPERO","text_entry":"Thou liest, malignant thing! Hast thou forgot"},{"line_id":91791,"play_name":"The Tempest","speech_number":66,"line_number":"1.2.304","speaker":"PROSPERO","text_entry":"The foul witch Sycorax, who with age and envy"},{"line_id":91792,"play_name":"The Tempest","speech_number":66,"line_number":"1.2.305","speaker":"PROSPERO","text_entry":"Was grown into a hoop? hast thou forgot her?"},{"line_id":91793,"play_name":"The Tempest","speech_number":67,"line_number":"1.2.306","speaker":"ARIEL","text_entry":"No, sir."},{"line_id":91794,"play_name":"The Tempest","speech_number":68,"line_number":"1.2.307","speaker":"PROSPERO","text_entry":"Thou hast. Where was she born? speak; tell me."},{"line_id":91795,"play_name":"The Tempest","speech_number":69,"line_number":"1.2.308","speaker":"ARIEL","text_entry":"Sir, in Argier."},{"line_id":91796,"play_name":"The Tempest","speech_number":70,"line_number":"1.2.309","speaker":"PROSPERO","text_entry":"O, was she so? I must"},{"line_id":91797,"play_name":"The Tempest","speech_number":70,"line_number":"1.2.310","speaker":"PROSPERO","text_entry":"Once in a month recount what thou hast been,"},{"line_id":91798,"play_name":"The Tempest","speech_number":70,"line_number":"1.2.311","speaker":"PROSPERO","text_entry":"Which thou forget'st. This damn'd witch Sycorax,"},{"line_id":91799,"play_name":"The Tempest","speech_number":70,"line_number":"1.2.312","speaker":"PROSPERO","text_entry":"For mischiefs manifold and sorceries terrible"},{"line_id":91800,"play_name":"The Tempest","speech_number":70,"line_number":"1.2.313","speaker":"PROSPERO","text_entry":"To enter human hearing, from Argier,"},{"line_id":91801,"play_name":"The Tempest","speech_number":70,"line_number":"1.2.314","speaker":"PROSPERO","text_entry":"Thou know'st, was banish'd: for one thing she did"},{"line_id":91802,"play_name":"The Tempest","speech_number":70,"line_number":"1.2.315","speaker":"PROSPERO","text_entry":"They would not take her life. Is not this true?"},{"line_id":91803,"play_name":"The Tempest","speech_number":71,"line_number":"1.2.316","speaker":"ARIEL","text_entry":"Ay, sir."},{"line_id":91804,"play_name":"The Tempest","speech_number":72,"line_number":"1.2.317","speaker":"PROSPERO","text_entry":"This blue-eyed hag was hither brought with child"},{"line_id":91805,"play_name":"The Tempest","speech_number":72,"line_number":"1.2.318","speaker":"PROSPERO","text_entry":"And here was left by the sailors. Thou, my slave,"},{"line_id":91806,"play_name":"The Tempest","speech_number":72,"line_number":"1.2.319","speaker":"PROSPERO","text_entry":"As thou report'st thyself, wast then her servant;"},{"line_id":91807,"play_name":"The Tempest","speech_number":72,"line_number":"1.2.320","speaker":"PROSPERO","text_entry":"And, for thou wast a spirit too delicate"},{"line_id":91808,"play_name":"The Tempest","speech_number":72,"line_number":"1.2.321","speaker":"PROSPERO","text_entry":"To act her earthy and abhorr'd commands,"},{"line_id":91809,"play_name":"The Tempest","speech_number":72,"line_number":"1.2.322","speaker":"PROSPERO","text_entry":"Refusing her grand hests, she did confine thee,"},{"line_id":91810,"play_name":"The Tempest","speech_number":72,"line_number":"1.2.323","speaker":"PROSPERO","text_entry":"By help of her more potent ministers"},{"line_id":91811,"play_name":"The Tempest","speech_number":72,"line_number":"1.2.324","speaker":"PROSPERO","text_entry":"And in her most unmitigable rage,"},{"line_id":91812,"play_name":"The Tempest","speech_number":72,"line_number":"1.2.325","speaker":"PROSPERO","text_entry":"Into a cloven pine; within which rift"},{"line_id":91813,"play_name":"The Tempest","speech_number":72,"line_number":"1.2.326","speaker":"PROSPERO","text_entry":"Imprison'd thou didst painfully remain"},{"line_id":91814,"play_name":"The Tempest","speech_number":72,"line_number":"1.2.327","speaker":"PROSPERO","text_entry":"A dozen years; within which space she died"},{"line_id":91815,"play_name":"The Tempest","speech_number":72,"line_number":"1.2.328","speaker":"PROSPERO","text_entry":"And left thee there; where thou didst vent thy groans"},{"line_id":91816,"play_name":"The Tempest","speech_number":72,"line_number":"1.2.329","speaker":"PROSPERO","text_entry":"As fast as mill-wheels strike. Then was this island--"},{"line_id":91817,"play_name":"The Tempest","speech_number":72,"line_number":"1.2.330","speaker":"PROSPERO","text_entry":"Save for the son that she did litter here,"},{"line_id":91818,"play_name":"The Tempest","speech_number":72,"line_number":"1.2.331","speaker":"PROSPERO","text_entry":"A freckled whelp hag-born--not honour'd with"},{"line_id":91819,"play_name":"The Tempest","speech_number":72,"line_number":"1.2.332","speaker":"PROSPERO","text_entry":"A human shape."},{"line_id":91820,"play_name":"The Tempest","speech_number":73,"line_number":"1.2.333","speaker":"ARIEL","text_entry":"Yes, Caliban her son."},{"line_id":91821,"play_name":"The Tempest","speech_number":74,"line_number":"1.2.334","speaker":"PROSPERO","text_entry":"Dull thing, I say so; he, that Caliban"},{"line_id":91822,"play_name":"The Tempest","speech_number":74,"line_number":"1.2.335","speaker":"PROSPERO","text_entry":"Whom now I keep in service. Thou best know'st"},{"line_id":91823,"play_name":"The Tempest","speech_number":74,"line_number":"1.2.336","speaker":"PROSPERO","text_entry":"What torment I did find thee in; thy groans"},{"line_id":91824,"play_name":"The Tempest","speech_number":74,"line_number":"1.2.337","speaker":"PROSPERO","text_entry":"Did make wolves howl and penetrate the breasts"},{"line_id":91825,"play_name":"The Tempest","speech_number":74,"line_number":"1.2.338","speaker":"PROSPERO","text_entry":"Of ever angry bears: it was a torment"},{"line_id":91826,"play_name":"The Tempest","speech_number":74,"line_number":"1.2.339","speaker":"PROSPERO","text_entry":"To lay upon the damn'd, which Sycorax"},{"line_id":91827,"play_name":"The Tempest","speech_number":74,"line_number":"1.2.340","speaker":"PROSPERO","text_entry":"Could not again undo: it was mine art,"},{"line_id":91828,"play_name":"The Tempest","speech_number":74,"line_number":"1.2.341","speaker":"PROSPERO","text_entry":"When I arrived and heard thee, that made gape"},{"line_id":91829,"play_name":"The Tempest","speech_number":74,"line_number":"1.2.342","speaker":"PROSPERO","text_entry":"The pine and let thee out."},{"line_id":91830,"play_name":"The Tempest","speech_number":75,"line_number":"1.2.343","speaker":"ARIEL","text_entry":"I thank thee, master."},{"line_id":91831,"play_name":"The Tempest","speech_number":76,"line_number":"1.2.344","speaker":"PROSPERO","text_entry":"If thou more murmur'st, I will rend an oak"},{"line_id":91832,"play_name":"The Tempest","speech_number":76,"line_number":"1.2.345","speaker":"PROSPERO","text_entry":"And peg thee in his knotty entrails till"},{"line_id":91833,"play_name":"The Tempest","speech_number":76,"line_number":"1.2.346","speaker":"PROSPERO","text_entry":"Thou hast howl'd away twelve winters."},{"line_id":91834,"play_name":"The Tempest","speech_number":77,"line_number":"1.2.347","speaker":"ARIEL","text_entry":"Pardon, master;"},{"line_id":91835,"play_name":"The Tempest","speech_number":77,"line_number":"1.2.348","speaker":"ARIEL","text_entry":"I will be correspondent to command"},{"line_id":91836,"play_name":"The Tempest","speech_number":77,"line_number":"1.2.349","speaker":"ARIEL","text_entry":"And do my spiriting gently."},{"line_id":91837,"play_name":"The Tempest","speech_number":78,"line_number":"1.2.350","speaker":"PROSPERO","text_entry":"Do so, and after two days"},{"line_id":91838,"play_name":"The Tempest","speech_number":78,"line_number":"1.2.351","speaker":"PROSPERO","text_entry":"I will discharge thee."},{"line_id":91839,"play_name":"The Tempest","speech_number":79,"line_number":"1.2.352","speaker":"ARIEL","text_entry":"That's my noble master!"},{"line_id":91840,"play_name":"The Tempest","speech_number":79,"line_number":"1.2.353","speaker":"ARIEL","text_entry":"What shall I do? say what; what shall I do?"},{"line_id":91841,"play_name":"The Tempest","speech_number":80,"line_number":"1.2.354","speaker":"PROSPERO","text_entry":"Go make thyself like a nymph o' the sea: be subject"},{"line_id":91842,"play_name":"The Tempest","speech_number":80,"line_number":"1.2.355","speaker":"PROSPERO","text_entry":"To no sight but thine and mine, invisible"},{"line_id":91843,"play_name":"The Tempest","speech_number":80,"line_number":"1.2.356","speaker":"PROSPERO","text_entry":"To every eyeball else. Go take this shape"},{"line_id":91844,"play_name":"The Tempest","speech_number":80,"line_number":"1.2.357","speaker":"PROSPERO","text_entry":"And hither come in't: go, hence with diligence!"},{"line_id":91845,"play_name":"The Tempest","speech_number":80,"line_number":"1.2.0","speaker":"PROSPERO","text_entry":"Exit ARIEL"},{"line_id":91846,"play_name":"The Tempest","speech_number":80,"line_number":"1.2.358","speaker":"PROSPERO","text_entry":"Awake, dear heart, awake! thou hast slept well; Awake!"},{"line_id":91847,"play_name":"The Tempest","speech_number":81,"line_number":"1.2.359","speaker":"MIRANDA","text_entry":"The strangeness of your story put"},{"line_id":91848,"play_name":"The Tempest","speech_number":81,"line_number":"1.2.360","speaker":"MIRANDA","text_entry":"Heaviness in me."},{"line_id":91849,"play_name":"The Tempest","speech_number":82,"line_number":"1.2.361","speaker":"PROSPERO","text_entry":"Shake it off. Come on;"},{"line_id":91850,"play_name":"The Tempest","speech_number":82,"line_number":"1.2.362","speaker":"PROSPERO","text_entry":"We'll visit Caliban my slave, who never"},{"line_id":91851,"play_name":"The Tempest","speech_number":82,"line_number":"1.2.363","speaker":"PROSPERO","text_entry":"Yields us kind answer."},{"line_id":91852,"play_name":"The Tempest","speech_number":83,"line_number":"1.2.364","speaker":"MIRANDA","text_entry":"'Tis a villain, sir,"},{"line_id":91853,"play_name":"The Tempest","speech_number":83,"line_number":"1.2.365","speaker":"MIRANDA","text_entry":"I do not love to look on."},{"line_id":91854,"play_name":"The Tempest","speech_number":84,"line_number":"1.2.366","speaker":"PROSPERO","text_entry":"But, as 'tis,"},{"line_id":91855,"play_name":"The Tempest","speech_number":84,"line_number":"1.2.367","speaker":"PROSPERO","text_entry":"We cannot miss him: he does make our fire,"},{"line_id":91856,"play_name":"The Tempest","speech_number":84,"line_number":"1.2.368","speaker":"PROSPERO","text_entry":"Fetch in our wood and serves in offices"},{"line_id":91857,"play_name":"The Tempest","speech_number":84,"line_number":"1.2.369","speaker":"PROSPERO","text_entry":"That profit us. What, ho! slave! Caliban!"},{"line_id":91858,"play_name":"The Tempest","speech_number":84,"line_number":"1.2.370","speaker":"PROSPERO","text_entry":"Thou earth, thou! speak."},{"line_id":91859,"play_name":"The Tempest","speech_number":85,"line_number":"1.2.371","speaker":"CALIBAN","text_entry":"[Within]  There's wood enough within."},{"line_id":91860,"play_name":"The Tempest","speech_number":86,"line_number":"1.2.372","speaker":"PROSPERO","text_entry":"Come forth, I say! there's other business for thee:"},{"line_id":91861,"play_name":"The Tempest","speech_number":86,"line_number":"1.2.373","speaker":"PROSPERO","text_entry":"Come, thou tortoise! when?"},{"line_id":91862,"play_name":"The Tempest","speech_number":86,"line_number":"1.2.0","speaker":"PROSPERO","text_entry":"Re-enter ARIEL like a water-nymph"},{"line_id":91863,"play_name":"The Tempest","speech_number":86,"line_number":"1.2.374","speaker":"PROSPERO","text_entry":"Fine apparition! My quaint Ariel,"},{"line_id":91864,"play_name":"The Tempest","speech_number":86,"line_number":"1.2.375","speaker":"PROSPERO","text_entry":"Hark in thine ear."},{"line_id":91865,"play_name":"The Tempest","speech_number":87,"line_number":"1.2.376","speaker":"ARIEL","text_entry":"My lord it shall be done."},{"line_id":91866,"play_name":"The Tempest","speech_number":87,"line_number":"1.2.0","speaker":"ARIEL","text_entry":"Exit"},{"line_id":91867,"play_name":"The Tempest","speech_number":88,"line_number":"1.2.377","speaker":"PROSPERO","text_entry":"Thou poisonous slave, got by the devil himself"},{"line_id":91868,"play_name":"The Tempest","speech_number":88,"line_number":"1.2.378","speaker":"PROSPERO","text_entry":"Upon thy wicked dam, come forth!"},{"line_id":91869,"play_name":"The Tempest","speech_number":88,"line_number":"1.2.0","speaker":"PROSPERO","text_entry":"Enter CALIBAN"},{"line_id":91870,"play_name":"The Tempest","speech_number":89,"line_number":"1.2.379","speaker":"CALIBAN","text_entry":"As wicked dew as e'er my mother brush'd"},{"line_id":91871,"play_name":"The Tempest","speech_number":89,"line_number":"1.2.380","speaker":"CALIBAN","text_entry":"With raven's feather from unwholesome fen"},{"line_id":91872,"play_name":"The Tempest","speech_number":89,"line_number":"1.2.381","speaker":"CALIBAN","text_entry":"Drop on you both! a south-west blow on ye"},{"line_id":91873,"play_name":"The Tempest","speech_number":89,"line_number":"1.2.382","speaker":"CALIBAN","text_entry":"And blister you all o'er!"},{"line_id":91874,"play_name":"The Tempest","speech_number":90,"line_number":"1.2.383","speaker":"PROSPERO","text_entry":"For this, be sure, to-night thou shalt have cramps,"},{"line_id":91875,"play_name":"The Tempest","speech_number":90,"line_number":"1.2.384","speaker":"PROSPERO","text_entry":"Side-stitches that shall pen thy breath up; urchins"},{"line_id":91876,"play_name":"The Tempest","speech_number":90,"line_number":"1.2.385","speaker":"PROSPERO","text_entry":"Shall, for that vast of night that they may work,"},{"line_id":91877,"play_name":"The Tempest","speech_number":90,"line_number":"1.2.386","speaker":"PROSPERO","text_entry":"All exercise on thee; thou shalt be pinch'd"},{"line_id":91878,"play_name":"The Tempest","speech_number":90,"line_number":"1.2.387","speaker":"PROSPERO","text_entry":"As thick as honeycomb, each pinch more stinging"},{"line_id":91879,"play_name":"The Tempest","speech_number":90,"line_number":"1.2.388","speaker":"PROSPERO","text_entry":"Than bees that made 'em."},{"line_id":91880,"play_name":"The Tempest","speech_number":91,"line_number":"1.2.389","speaker":"CALIBAN","text_entry":"I must eat my dinner."},{"line_id":91881,"play_name":"The Tempest","speech_number":91,"line_number":"1.2.390","speaker":"CALIBAN","text_entry":"This island's mine, by Sycorax my mother,"},{"line_id":91882,"play_name":"The Tempest","speech_number":91,"line_number":"1.2.391","speaker":"CALIBAN","text_entry":"Which thou takest from me. When thou camest first,"},{"line_id":91883,"play_name":"The Tempest","speech_number":91,"line_number":"1.2.392","speaker":"CALIBAN","text_entry":"Thou strokedst me and madest much of me, wouldst give me"},{"line_id":91884,"play_name":"The Tempest","speech_number":91,"line_number":"1.2.393","speaker":"CALIBAN","text_entry":"Water with berries in't, and teach me how"},{"line_id":91885,"play_name":"The Tempest","speech_number":91,"line_number":"1.2.394","speaker":"CALIBAN","text_entry":"To name the bigger light, and how the less,"},{"line_id":91886,"play_name":"The Tempest","speech_number":91,"line_number":"1.2.395","speaker":"CALIBAN","text_entry":"That burn by day and night: and then I loved thee"},{"line_id":91887,"play_name":"The Tempest","speech_number":91,"line_number":"1.2.396","speaker":"CALIBAN","text_entry":"And show'd thee all the qualities o' the isle,"},{"line_id":91888,"play_name":"The Tempest","speech_number":91,"line_number":"1.2.397","speaker":"CALIBAN","text_entry":"The fresh springs, brine-pits, barren place and fertile:"},{"line_id":91889,"play_name":"The Tempest","speech_number":91,"line_number":"1.2.398","speaker":"CALIBAN","text_entry":"Cursed be I that did so! All the charms"},{"line_id":91890,"play_name":"The Tempest","speech_number":91,"line_number":"1.2.399","speaker":"CALIBAN","text_entry":"Of Sycorax, toads, beetles, bats, light on you!"},{"line_id":91891,"play_name":"The Tempest","speech_number":91,"line_number":"1.2.400","speaker":"CALIBAN","text_entry":"For I am all the subjects that you have,"},{"line_id":91892,"play_name":"The Tempest","speech_number":91,"line_number":"1.2.401","speaker":"CALIBAN","text_entry":"Which first was mine own king: and here you sty me"},{"line_id":91893,"play_name":"The Tempest","speech_number":91,"line_number":"1.2.402","speaker":"CALIBAN","text_entry":"In this hard rock, whiles you do keep from me"},{"line_id":91894,"play_name":"The Tempest","speech_number":91,"line_number":"1.2.403","speaker":"CALIBAN","text_entry":"The rest o' the island."},{"line_id":91895,"play_name":"The Tempest","speech_number":92,"line_number":"1.2.404","speaker":"PROSPERO","text_entry":"Thou most lying slave,"},{"line_id":91896,"play_name":"The Tempest","speech_number":92,"line_number":"1.2.405","speaker":"PROSPERO","text_entry":"Whom stripes may move, not kindness! I have used thee,"},{"line_id":91897,"play_name":"The Tempest","speech_number":92,"line_number":"1.2.406","speaker":"PROSPERO","text_entry":"Filth as thou art, with human care, and lodged thee"},{"line_id":91898,"play_name":"The Tempest","speech_number":92,"line_number":"1.2.407","speaker":"PROSPERO","text_entry":"In mine own cell, till thou didst seek to violate"},{"line_id":91899,"play_name":"The Tempest","speech_number":92,"line_number":"1.2.408","speaker":"PROSPERO","text_entry":"The honour of my child."},{"line_id":91900,"play_name":"The Tempest","speech_number":93,"line_number":"1.2.409","speaker":"CALIBAN","text_entry":"O ho, O ho! would't had been done!"},{"line_id":91901,"play_name":"The Tempest","speech_number":93,"line_number":"1.2.410","speaker":"CALIBAN","text_entry":"Thou didst prevent me; I had peopled else"},{"line_id":91902,"play_name":"The Tempest","speech_number":93,"line_number":"1.2.411","speaker":"CALIBAN","text_entry":"This isle with Calibans."},{"line_id":91903,"play_name":"The Tempest","speech_number":94,"line_number":"1.2.412","speaker":"PROSPERO","text_entry":"Abhorred slave,"},{"line_id":91904,"play_name":"The Tempest","speech_number":94,"line_number":"1.2.413","speaker":"PROSPERO","text_entry":"Which any print of goodness wilt not take,"},{"line_id":91905,"play_name":"The Tempest","speech_number":94,"line_number":"1.2.414","speaker":"PROSPERO","text_entry":"Being capable of all ill! I pitied thee,"},{"line_id":91906,"play_name":"The Tempest","speech_number":94,"line_number":"1.2.415","speaker":"PROSPERO","text_entry":"Took pains to make thee speak, taught thee each hour"},{"line_id":91907,"play_name":"The Tempest","speech_number":94,"line_number":"1.2.416","speaker":"PROSPERO","text_entry":"One thing or other: when thou didst not, savage,"},{"line_id":91908,"play_name":"The Tempest","speech_number":94,"line_number":"1.2.417","speaker":"PROSPERO","text_entry":"Know thine own meaning, but wouldst gabble like"},{"line_id":91909,"play_name":"The Tempest","speech_number":94,"line_number":"1.2.418","speaker":"PROSPERO","text_entry":"A thing most brutish, I endow'd thy purposes"},{"line_id":91910,"play_name":"The Tempest","speech_number":94,"line_number":"1.2.419","speaker":"PROSPERO","text_entry":"With words that made them known. But thy vile race,"},{"line_id":91911,"play_name":"The Tempest","speech_number":94,"line_number":"1.2.420","speaker":"PROSPERO","text_entry":"Though thou didst learn, had that in't which"},{"line_id":91912,"play_name":"The Tempest","speech_number":94,"line_number":"1.2.421","speaker":"PROSPERO","text_entry":"good natures"},{"line_id":91913,"play_name":"The Tempest","speech_number":94,"line_number":"1.2.422","speaker":"PROSPERO","text_entry":"Could not abide to be with; therefore wast thou"},{"line_id":91914,"play_name":"The Tempest","speech_number":94,"line_number":"1.2.423","speaker":"PROSPERO","text_entry":"Deservedly confined into this rock,"},{"line_id":91915,"play_name":"The Tempest","speech_number":94,"line_number":"1.2.424","speaker":"PROSPERO","text_entry":"Who hadst deserved more than a prison."},{"line_id":91916,"play_name":"The Tempest","speech_number":95,"line_number":"1.2.425","speaker":"CALIBAN","text_entry":"You taught me language; and my profit on't"},{"line_id":91917,"play_name":"The Tempest","speech_number":95,"line_number":"1.2.426","speaker":"CALIBAN","text_entry":"Is, I know how to curse. The red plague rid you"},{"line_id":91918,"play_name":"The Tempest","speech_number":95,"line_number":"1.2.427","speaker":"CALIBAN","text_entry":"For learning me your language!"},{"line_id":91919,"play_name":"The Tempest","speech_number":96,"line_number":"1.2.428","speaker":"PROSPERO","text_entry":"Hag-seed, hence!"},{"line_id":91920,"play_name":"The Tempest","speech_number":96,"line_number":"1.2.429","speaker":"PROSPERO","text_entry":"Fetch us in fuel; and be quick, thou'rt best,"},{"line_id":91921,"play_name":"The Tempest","speech_number":96,"line_number":"1.2.430","speaker":"PROSPERO","text_entry":"To answer other business. Shrug'st thou, malice?"},{"line_id":91922,"play_name":"The Tempest","speech_number":96,"line_number":"1.2.431","speaker":"PROSPERO","text_entry":"If thou neglect'st or dost unwillingly"},{"line_id":91923,"play_name":"The Tempest","speech_number":96,"line_number":"1.2.432","speaker":"PROSPERO","text_entry":"What I command, I'll rack thee with old cramps,"},{"line_id":91924,"play_name":"The Tempest","speech_number":96,"line_number":"1.2.433","speaker":"PROSPERO","text_entry":"Fill all thy bones with aches, make thee roar"},{"line_id":91925,"play_name":"The Tempest","speech_number":96,"line_number":"1.2.434","speaker":"PROSPERO","text_entry":"That beasts shall tremble at thy din."},{"line_id":91926,"play_name":"The Tempest","speech_number":97,"line_number":"1.2.435","speaker":"CALIBAN","text_entry":"No, pray thee."},{"line_id":91927,"play_name":"The Tempest","speech_number":97,"line_number":"1.2.0","speaker":"CALIBAN","text_entry":"Aside"},{"line_id":91928,"play_name":"The Tempest","speech_number":97,"line_number":"1.2.436","speaker":"CALIBAN","text_entry":"I must obey: his art is of such power,"},{"line_id":91929,"play_name":"The Tempest","speech_number":97,"line_number":"1.2.437","speaker":"CALIBAN","text_entry":"It would control my dam's god, Setebos,"},{"line_id":91930,"play_name":"The Tempest","speech_number":97,"line_number":"1.2.438","speaker":"CALIBAN","text_entry":"and make a vassal of him."},{"line_id":91931,"play_name":"The Tempest","speech_number":98,"line_number":"1.2.439","speaker":"PROSPERO","text_entry":"So, slave; hence!"},{"line_id":91932,"play_name":"The Tempest","speech_number":98,"line_number":"1.2.0","speaker":"PROSPERO","text_entry":"Exit CALIBAN"},{"line_id":91933,"play_name":"The Tempest","speech_number":98,"line_number":"1.2.0","speaker":"PROSPERO","text_entry":"Re-enter ARIEL, invisible, playing and singing; FERDINAND following"},{"line_id":91934,"play_name":"The Tempest","speech_number":98,"line_number":"1.2.440","speaker":"PROSPERO","text_entry":"ARIEL'S song."},{"line_id":91935,"play_name":"The Tempest","speech_number":98,"line_number":"1.2.441","speaker":"PROSPERO","text_entry":"Come unto these yellow sands,"},{"line_id":91936,"play_name":"The Tempest","speech_number":98,"line_number":"1.2.442","speaker":"PROSPERO","text_entry":"And then take hands:"},{"line_id":91937,"play_name":"The Tempest","speech_number":98,"line_number":"1.2.443","speaker":"PROSPERO","text_entry":"Courtsied when you have and kiss'd"},{"line_id":91938,"play_name":"The Tempest","speech_number":98,"line_number":"1.2.444","speaker":"PROSPERO","text_entry":"The wild waves whist,"},{"line_id":91939,"play_name":"The Tempest","speech_number":98,"line_number":"1.2.445","speaker":"PROSPERO","text_entry":"Foot it featly here and there;"},{"line_id":91940,"play_name":"The Tempest","speech_number":98,"line_number":"1.2.446","speaker":"PROSPERO","text_entry":"And, sweet sprites, the burthen bear."},{"line_id":91941,"play_name":"The Tempest","speech_number":98,"line_number":"1.2.447","speaker":"PROSPERO","text_entry":"Hark, hark!"},{"line_id":91942,"play_name":"The Tempest","speech_number":98,"line_number":"1.2.447","speaker":"PROSPERO","text_entry":"Burthen [dispersedly, within"},{"line_id":91943,"play_name":"The Tempest","speech_number":98,"line_number":"1.2.448","speaker":"PROSPERO","text_entry":"The watch-dogs bark!"},{"line_id":91944,"play_name":"The Tempest","speech_number":98,"line_number":"1.2.0","speaker":"PROSPERO","text_entry":"Burthen Bow-wow"},{"line_id":91945,"play_name":"The Tempest","speech_number":98,"line_number":"1.2.449","speaker":"PROSPERO","text_entry":"Hark, hark! I hear"},{"line_id":91946,"play_name":"The Tempest","speech_number":98,"line_number":"1.2.450","speaker":"PROSPERO","text_entry":"The strain of strutting chanticleer"},{"line_id":91947,"play_name":"The Tempest","speech_number":98,"line_number":"1.2.451","speaker":"PROSPERO","text_entry":"Cry, Cock-a-diddle-dow."},{"line_id":91948,"play_name":"The Tempest","speech_number":99,"line_number":"1.2.452","speaker":"FERDINAND","text_entry":"Where should this music be? i' the air or the earth?"},{"line_id":91949,"play_name":"The Tempest","speech_number":99,"line_number":"1.2.453","speaker":"FERDINAND","text_entry":"It sounds no more: and sure, it waits upon"},{"line_id":91950,"play_name":"The Tempest","speech_number":99,"line_number":"1.2.454","speaker":"FERDINAND","text_entry":"Some god o' the island. Sitting on a bank,"},{"line_id":91951,"play_name":"The Tempest","speech_number":99,"line_number":"1.2.455","speaker":"FERDINAND","text_entry":"Weeping again the king my father's wreck,"},{"line_id":91952,"play_name":"The Tempest","speech_number":99,"line_number":"1.2.456","speaker":"FERDINAND","text_entry":"This music crept by me upon the waters,"},{"line_id":91953,"play_name":"The Tempest","speech_number":99,"line_number":"1.2.457","speaker":"FERDINAND","text_entry":"Allaying both their fury and my passion"},{"line_id":91954,"play_name":"The Tempest","speech_number":99,"line_number":"1.2.458","speaker":"FERDINAND","text_entry":"With its sweet air: thence I have follow'd it,"},{"line_id":91955,"play_name":"The Tempest","speech_number":99,"line_number":"1.2.459","speaker":"FERDINAND","text_entry":"Or it hath drawn me rather. But 'tis gone."},{"line_id":91956,"play_name":"The Tempest","speech_number":99,"line_number":"1.2.460","speaker":"FERDINAND","text_entry":"No, it begins again."},{"line_id":91957,"play_name":"The Tempest","speech_number":99,"line_number":"1.2.0","speaker":"FERDINAND","text_entry":"ARIEL sings"},{"line_id":91958,"play_name":"The Tempest","speech_number":99,"line_number":"1.2.461","speaker":"FERDINAND","text_entry":"Full fathom five thy father lies;"},{"line_id":91959,"play_name":"The Tempest","speech_number":99,"line_number":"1.2.462","speaker":"FERDINAND","text_entry":"Of his bones are coral made;"},{"line_id":91960,"play_name":"The Tempest","speech_number":99,"line_number":"1.2.463","speaker":"FERDINAND","text_entry":"Those are pearls that were his eyes:"},{"line_id":91961,"play_name":"The Tempest","speech_number":99,"line_number":"1.2.464","speaker":"FERDINAND","text_entry":"Nothing of him that doth fade"},{"line_id":91962,"play_name":"The Tempest","speech_number":99,"line_number":"1.2.465","speaker":"FERDINAND","text_entry":"But doth suffer a sea-change"},{"line_id":91963,"play_name":"The Tempest","speech_number":99,"line_number":"1.2.466","speaker":"FERDINAND","text_entry":"Into something rich and strange."},{"line_id":91964,"play_name":"The Tempest","speech_number":99,"line_number":"1.2.467","speaker":"FERDINAND","text_entry":"Sea-nymphs hourly ring his knell"},{"line_id":91965,"play_name":"The Tempest","speech_number":99,"line_number":"1.2.0","speaker":"FERDINAND","text_entry":"Burthen Ding-dong"},{"line_id":91966,"play_name":"The Tempest","speech_number":99,"line_number":"1.2.468","speaker":"FERDINAND","text_entry":"Hark! now I hear them,--Ding-dong, bell."},{"line_id":91967,"play_name":"The Tempest","speech_number":100,"line_number":"1.2.469","speaker":"FERDINAND","text_entry":"The ditty does remember my drown'd father."},{"line_id":91968,"play_name":"The Tempest","speech_number":100,"line_number":"1.2.470","speaker":"FERDINAND","text_entry":"This is no mortal business, nor no sound"},{"line_id":91969,"play_name":"The Tempest","speech_number":100,"line_number":"1.2.471","speaker":"FERDINAND","text_entry":"That the earth owes. I hear it now above me."},{"line_id":91970,"play_name":"The Tempest","speech_number":101,"line_number":"1.2.472","speaker":"PROSPERO","text_entry":"The fringed curtains of thine eye advance"},{"line_id":91971,"play_name":"The Tempest","speech_number":101,"line_number":"1.2.473","speaker":"PROSPERO","text_entry":"And say what thou seest yond."},{"line_id":91972,"play_name":"The Tempest","speech_number":102,"line_number":"1.2.474","speaker":"MIRANDA","text_entry":"What is't? a spirit?"},{"line_id":91973,"play_name":"The Tempest","speech_number":102,"line_number":"1.2.475","speaker":"MIRANDA","text_entry":"Lord, how it looks about! Believe me, sir,"},{"line_id":91974,"play_name":"The Tempest","speech_number":102,"line_number":"1.2.476","speaker":"MIRANDA","text_entry":"It carries a brave form. But 'tis a spirit."},{"line_id":91975,"play_name":"The Tempest","speech_number":103,"line_number":"1.2.477","speaker":"PROSPERO","text_entry":"No, wench; it eats and sleeps and hath such senses"},{"line_id":91976,"play_name":"The Tempest","speech_number":103,"line_number":"1.2.478","speaker":"PROSPERO","text_entry":"As we have, such. This gallant which thou seest"},{"line_id":91977,"play_name":"The Tempest","speech_number":103,"line_number":"1.2.479","speaker":"PROSPERO","text_entry":"Was in the wreck; and, but he's something stain'd"},{"line_id":91978,"play_name":"The Tempest","speech_number":103,"line_number":"1.2.480","speaker":"PROSPERO","text_entry":"With grief that's beauty's canker, thou mightst call him"},{"line_id":91979,"play_name":"The Tempest","speech_number":103,"line_number":"1.2.481","speaker":"PROSPERO","text_entry":"A goodly person: he hath lost his fellows"},{"line_id":91980,"play_name":"The Tempest","speech_number":103,"line_number":"1.2.482","speaker":"PROSPERO","text_entry":"And strays about to find 'em."},{"line_id":91981,"play_name":"The Tempest","speech_number":104,"line_number":"1.2.483","speaker":"MIRANDA","text_entry":"I might call him"},{"line_id":91982,"play_name":"The Tempest","speech_number":104,"line_number":"1.2.484","speaker":"MIRANDA","text_entry":"A thing divine, for nothing natural"},{"line_id":91983,"play_name":"The Tempest","speech_number":104,"line_number":"1.2.485","speaker":"MIRANDA","text_entry":"I ever saw so noble."},{"line_id":91984,"play_name":"The Tempest","speech_number":105,"line_number":"1.2.486","speaker":"PROSPERO","text_entry":"[Aside] It goes on, I see,"},{"line_id":91985,"play_name":"The Tempest","speech_number":105,"line_number":"1.2.487","speaker":"PROSPERO","text_entry":"As my soul prompts it. Spirit, fine spirit! I'll free thee"},{"line_id":91986,"play_name":"The Tempest","speech_number":105,"line_number":"1.2.488","speaker":"PROSPERO","text_entry":"Within two days for this."},{"line_id":91987,"play_name":"The Tempest","speech_number":106,"line_number":"1.2.489","speaker":"FERDINAND","text_entry":"Most sure, the goddess"},{"line_id":91988,"play_name":"The Tempest","speech_number":106,"line_number":"1.2.490","speaker":"FERDINAND","text_entry":"On whom these airs attend! Vouchsafe my prayer"},{"line_id":91989,"play_name":"The Tempest","speech_number":106,"line_number":"1.2.491","speaker":"FERDINAND","text_entry":"May know if you remain upon this island;"},{"line_id":91990,"play_name":"The Tempest","speech_number":106,"line_number":"1.2.492","speaker":"FERDINAND","text_entry":"And that you will some good instruction give"},{"line_id":91991,"play_name":"The Tempest","speech_number":106,"line_number":"1.2.493","speaker":"FERDINAND","text_entry":"How I may bear me here: my prime request,"},{"line_id":91992,"play_name":"The Tempest","speech_number":106,"line_number":"1.2.494","speaker":"FERDINAND","text_entry":"Which I do last pronounce, is, O you wonder!"},{"line_id":91993,"play_name":"The Tempest","speech_number":106,"line_number":"1.2.495","speaker":"FERDINAND","text_entry":"If you be maid or no?"},{"line_id":91994,"play_name":"The Tempest","speech_number":107,"line_number":"1.2.496","speaker":"MIRANDA","text_entry":"No wonder, sir;"},{"line_id":91995,"play_name":"The Tempest","speech_number":107,"line_number":"1.2.497","speaker":"MIRANDA","text_entry":"But certainly a maid."},{"line_id":91996,"play_name":"The Tempest","speech_number":108,"line_number":"1.2.498","speaker":"FERDINAND","text_entry":"My language! heavens!"},{"line_id":91997,"play_name":"The Tempest","speech_number":108,"line_number":"1.2.499","speaker":"FERDINAND","text_entry":"I am the best of them that speak this speech,"},{"line_id":91998,"play_name":"The Tempest","speech_number":108,"line_number":"1.2.500","speaker":"FERDINAND","text_entry":"Were I but where 'tis spoken."},{"line_id":91999,"play_name":"The Tempest","speech_number":109,"line_number":"1.2.501","speaker":"PROSPERO","text_entry":"How? the best?"},{"line_id":92000,"play_name":"The Tempest","speech_number":109,"line_number":"1.2.502","speaker":"PROSPERO","text_entry":"What wert thou, if the King of Naples heard thee?"},{"line_id":92001,"play_name":"The Tempest","speech_number":110,"line_number":"1.2.503","speaker":"FERDINAND","text_entry":"A single thing, as I am now, that wonders"},{"line_id":92002,"play_name":"The Tempest","speech_number":110,"line_number":"1.2.504","speaker":"FERDINAND","text_entry":"To hear thee speak of Naples. He does hear me;"},{"line_id":92003,"play_name":"The Tempest","speech_number":110,"line_number":"1.2.505","speaker":"FERDINAND","text_entry":"And that he does I weep: myself am Naples,"},{"line_id":92004,"play_name":"The Tempest","speech_number":110,"line_number":"1.2.506","speaker":"FERDINAND","text_entry":"Who with mine eyes, never since at ebb, beheld"},{"line_id":92005,"play_name":"The Tempest","speech_number":110,"line_number":"1.2.507","speaker":"FERDINAND","text_entry":"The king my father wreck'd."},{"line_id":92006,"play_name":"The Tempest","speech_number":111,"line_number":"1.2.508","speaker":"MIRANDA","text_entry":"Alack, for mercy!"},{"line_id":92007,"play_name":"The Tempest","speech_number":112,"line_number":"1.2.509","speaker":"FERDINAND","text_entry":"Yes, faith, and all his lords; the Duke of Milan"},{"line_id":92008,"play_name":"The Tempest","speech_number":112,"line_number":"1.2.510","speaker":"FERDINAND","text_entry":"And his brave son being twain."},{"line_id":92009,"play_name":"The Tempest","speech_number":113,"line_number":"1.2.511","speaker":"PROSPERO","text_entry":"[Aside] The Duke of Milan"},{"line_id":92010,"play_name":"The Tempest","speech_number":113,"line_number":"1.2.512","speaker":"PROSPERO","text_entry":"And his more braver daughter could control thee,"},{"line_id":92011,"play_name":"The Tempest","speech_number":113,"line_number":"1.2.513","speaker":"PROSPERO","text_entry":"If now 'twere fit to do't. At the first sight"},{"line_id":92012,"play_name":"The Tempest","speech_number":113,"line_number":"1.2.514","speaker":"PROSPERO","text_entry":"They have changed eyes. Delicate Ariel,"},{"line_id":92013,"play_name":"The Tempest","speech_number":113,"line_number":"1.2.515","speaker":"PROSPERO","text_entry":"I'll set thee free for this."},{"line_id":92014,"play_name":"The Tempest","speech_number":113,"line_number":"1.2.0","speaker":"PROSPERO","text_entry":"To FERDINAND"},{"line_id":92015,"play_name":"The Tempest","speech_number":113,"line_number":"1.2.516","speaker":"PROSPERO","text_entry":"A word, good sir;"},{"line_id":92016,"play_name":"The Tempest","speech_number":113,"line_number":"1.2.517","speaker":"PROSPERO","text_entry":"I fear you have done yourself some wrong: a word."},{"line_id":92017,"play_name":"The Tempest","speech_number":114,"line_number":"1.2.518","speaker":"MIRANDA","text_entry":"Why speaks my father so ungently? This"},{"line_id":92018,"play_name":"The Tempest","speech_number":114,"line_number":"1.2.519","speaker":"MIRANDA","text_entry":"Is the third man that e'er I saw, the first"},{"line_id":92019,"play_name":"The Tempest","speech_number":114,"line_number":"1.2.520","speaker":"MIRANDA","text_entry":"That e'er I sigh'd for: pity move my father"},{"line_id":92020,"play_name":"The Tempest","speech_number":114,"line_number":"1.2.521","speaker":"MIRANDA","text_entry":"To be inclined my way!"},{"line_id":92021,"play_name":"The Tempest","speech_number":115,"line_number":"1.2.522","speaker":"FERDINAND","text_entry":"O, if a virgin,"},{"line_id":92022,"play_name":"The Tempest","speech_number":115,"line_number":"1.2.523","speaker":"FERDINAND","text_entry":"And your affection not gone forth, I'll make you"},{"line_id":92023,"play_name":"The Tempest","speech_number":115,"line_number":"1.2.524","speaker":"FERDINAND","text_entry":"The queen of Naples."},{"line_id":92024,"play_name":"The Tempest","speech_number":116,"line_number":"1.2.525","speaker":"PROSPERO","text_entry":"Soft, sir! one word more."},{"line_id":92025,"play_name":"The Tempest","speech_number":116,"line_number":"1.2.0","speaker":"PROSPERO","text_entry":"Aside"},{"line_id":92026,"play_name":"The Tempest","speech_number":116,"line_number":"1.2.526","speaker":"PROSPERO","text_entry":"They are both in either's powers; but this swift business"},{"line_id":92027,"play_name":"The Tempest","speech_number":116,"line_number":"1.2.527","speaker":"PROSPERO","text_entry":"I must uneasy make, lest too light winning"},{"line_id":92028,"play_name":"The Tempest","speech_number":116,"line_number":"1.2.528","speaker":"PROSPERO","text_entry":"Make the prize light."},{"line_id":92029,"play_name":"The Tempest","speech_number":116,"line_number":"1.2.0","speaker":"PROSPERO","text_entry":"To FERDINAND"},{"line_id":92030,"play_name":"The Tempest","speech_number":116,"line_number":"1.2.529","speaker":"PROSPERO","text_entry":"One word more; I charge thee"},{"line_id":92031,"play_name":"The Tempest","speech_number":116,"line_number":"1.2.530","speaker":"PROSPERO","text_entry":"That thou attend me: thou dost here usurp"},{"line_id":92032,"play_name":"The Tempest","speech_number":116,"line_number":"1.2.531","speaker":"PROSPERO","text_entry":"The name thou owest not; and hast put thyself"},{"line_id":92033,"play_name":"The Tempest","speech_number":116,"line_number":"1.2.532","speaker":"PROSPERO","text_entry":"Upon this island as a spy, to win it"},{"line_id":92034,"play_name":"The Tempest","speech_number":116,"line_number":"1.2.533","speaker":"PROSPERO","text_entry":"From me, the lord on't."},{"line_id":92035,"play_name":"The Tempest","speech_number":117,"line_number":"1.2.534","speaker":"FERDINAND","text_entry":"No, as I am a man."},{"line_id":92036,"play_name":"The Tempest","speech_number":118,"line_number":"1.2.535","speaker":"MIRANDA","text_entry":"There's nothing ill can dwell in such a temple:"},{"line_id":92037,"play_name":"The Tempest","speech_number":118,"line_number":"1.2.536","speaker":"MIRANDA","text_entry":"If the ill spirit have so fair a house,"},{"line_id":92038,"play_name":"The Tempest","speech_number":118,"line_number":"1.2.537","speaker":"MIRANDA","text_entry":"Good things will strive to dwell with't."},{"line_id":92039,"play_name":"The Tempest","speech_number":119,"line_number":"1.2.538","speaker":"PROSPERO","text_entry":"Follow me."},{"line_id":92040,"play_name":"The Tempest","speech_number":119,"line_number":"1.2.539","speaker":"PROSPERO","text_entry":"Speak not you for him; he's a traitor. Come;"},{"line_id":92041,"play_name":"The Tempest","speech_number":119,"line_number":"1.2.540","speaker":"PROSPERO","text_entry":"I'll manacle thy neck and feet together:"},{"line_id":92042,"play_name":"The Tempest","speech_number":119,"line_number":"1.2.541","speaker":"PROSPERO","text_entry":"Sea-water shalt thou drink; thy food shall be"},{"line_id":92043,"play_name":"The Tempest","speech_number":119,"line_number":"1.2.542","speaker":"PROSPERO","text_entry":"The fresh-brook muscles, wither'd roots and husks"},{"line_id":92044,"play_name":"The Tempest","speech_number":119,"line_number":"1.2.543","speaker":"PROSPERO","text_entry":"Wherein the acorn cradled. Follow."},{"line_id":92045,"play_name":"The Tempest","speech_number":120,"line_number":"1.2.544","speaker":"FERDINAND","text_entry":"No;"},{"line_id":92046,"play_name":"The Tempest","speech_number":120,"line_number":"1.2.545","speaker":"FERDINAND","text_entry":"I will resist such entertainment till"},{"line_id":92047,"play_name":"The Tempest","speech_number":120,"line_number":"1.2.546","speaker":"FERDINAND","text_entry":"Mine enemy has more power."},{"line_id":92048,"play_name":"The Tempest","speech_number":120,"line_number":"1.2.0","speaker":"FERDINAND","text_entry":"Draws, and is charmed from moving"},{"line_id":92049,"play_name":"The Tempest","speech_number":121,"line_number":"1.2.547","speaker":"MIRANDA","text_entry":"O dear father,"},{"line_id":92050,"play_name":"The Tempest","speech_number":121,"line_number":"1.2.548","speaker":"MIRANDA","text_entry":"Make not too rash a trial of him, for"},{"line_id":92051,"play_name":"The Tempest","speech_number":121,"line_number":"1.2.549","speaker":"MIRANDA","text_entry":"He's gentle and not fearful."},{"line_id":92052,"play_name":"The Tempest","speech_number":122,"line_number":"1.2.550","speaker":"PROSPERO","text_entry":"What? I say,"},{"line_id":92053,"play_name":"The Tempest","speech_number":122,"line_number":"1.2.551","speaker":"PROSPERO","text_entry":"My foot my tutor? Put thy sword up, traitor;"},{"line_id":92054,"play_name":"The Tempest","speech_number":122,"line_number":"1.2.552","speaker":"PROSPERO","text_entry":"Who makest a show but darest not strike, thy conscience"},{"line_id":92055,"play_name":"The Tempest","speech_number":122,"line_number":"1.2.553","speaker":"PROSPERO","text_entry":"Is so possess'd with guilt: come from thy ward,"},{"line_id":92056,"play_name":"The Tempest","speech_number":122,"line_number":"1.2.554","speaker":"PROSPERO","text_entry":"For I can here disarm thee with this stick"},{"line_id":92057,"play_name":"The Tempest","speech_number":122,"line_number":"1.2.555","speaker":"PROSPERO","text_entry":"And make thy weapon drop."},{"line_id":92058,"play_name":"The Tempest","speech_number":123,"line_number":"1.2.556","speaker":"MIRANDA","text_entry":"Beseech you, father."},{"line_id":92059,"play_name":"The Tempest","speech_number":124,"line_number":"1.2.557","speaker":"PROSPERO","text_entry":"Hence! hang not on my garments."},{"line_id":92060,"play_name":"The Tempest","speech_number":125,"line_number":"1.2.558","speaker":"MIRANDA","text_entry":"Sir, have pity;"},{"line_id":92061,"play_name":"The Tempest","speech_number":125,"line_number":"1.2.559","speaker":"MIRANDA","text_entry":"I'll be his surety."},{"line_id":92062,"play_name":"The Tempest","speech_number":126,"line_number":"1.2.560","speaker":"PROSPERO","text_entry":"Silence! one word more"},{"line_id":92063,"play_name":"The Tempest","speech_number":126,"line_number":"1.2.561","speaker":"PROSPERO","text_entry":"Shall make me chide thee, if not hate thee. What!"},{"line_id":92064,"play_name":"The Tempest","speech_number":126,"line_number":"1.2.562","speaker":"PROSPERO","text_entry":"An advocate for an imposter! hush!"},{"line_id":92065,"play_name":"The Tempest","speech_number":126,"line_number":"1.2.563","speaker":"PROSPERO","text_entry":"Thou think'st there is no more such shapes as he,"},{"line_id":92066,"play_name":"The Tempest","speech_number":126,"line_number":"1.2.564","speaker":"PROSPERO","text_entry":"Having seen but him and Caliban: foolish wench!"},{"line_id":92067,"play_name":"The Tempest","speech_number":126,"line_number":"1.2.565","speaker":"PROSPERO","text_entry":"To the most of men this is a Caliban"},{"line_id":92068,"play_name":"The Tempest","speech_number":126,"line_number":"1.2.566","speaker":"PROSPERO","text_entry":"And they to him are angels."},{"line_id":92069,"play_name":"The Tempest","speech_number":127,"line_number":"1.2.567","speaker":"MIRANDA","text_entry":"My affections"},{"line_id":92070,"play_name":"The Tempest","speech_number":127,"line_number":"1.2.568","speaker":"MIRANDA","text_entry":"Are then most humble; I have no ambition"},{"line_id":92071,"play_name":"The Tempest","speech_number":127,"line_number":"1.2.569","speaker":"MIRANDA","text_entry":"To see a goodlier man."},{"line_id":92072,"play_name":"The Tempest","speech_number":128,"line_number":"1.2.570","speaker":"PROSPERO","text_entry":"Come on; obey:"},{"line_id":92073,"play_name":"The Tempest","speech_number":128,"line_number":"1.2.571","speaker":"PROSPERO","text_entry":"Thy nerves are in their infancy again"},{"line_id":92074,"play_name":"The Tempest","speech_number":128,"line_number":"1.2.572","speaker":"PROSPERO","text_entry":"And have no vigour in them."},{"line_id":92075,"play_name":"The Tempest","speech_number":129,"line_number":"1.2.573","speaker":"FERDINAND","text_entry":"So they are;"},{"line_id":92076,"play_name":"The Tempest","speech_number":129,"line_number":"1.2.574","speaker":"FERDINAND","text_entry":"My spirits, as in a dream, are all bound up."},{"line_id":92077,"play_name":"The Tempest","speech_number":129,"line_number":"1.2.575","speaker":"FERDINAND","text_entry":"My father's loss, the weakness which I feel,"},{"line_id":92078,"play_name":"The Tempest","speech_number":129,"line_number":"1.2.576","speaker":"FERDINAND","text_entry":"The wreck of all my friends, nor this man's threats,"},{"line_id":92079,"play_name":"The Tempest","speech_number":129,"line_number":"1.2.577","speaker":"FERDINAND","text_entry":"To whom I am subdued, are but light to me,"},{"line_id":92080,"play_name":"The Tempest","speech_number":129,"line_number":"1.2.578","speaker":"FERDINAND","text_entry":"Might I but through my prison once a day"},{"line_id":92081,"play_name":"The Tempest","speech_number":129,"line_number":"1.2.579","speaker":"FERDINAND","text_entry":"Behold this maid: all corners else o' the earth"},{"line_id":92082,"play_name":"The Tempest","speech_number":129,"line_number":"1.2.580","speaker":"FERDINAND","text_entry":"Let liberty make use of; space enough"},{"line_id":92083,"play_name":"The Tempest","speech_number":129,"line_number":"1.2.581","speaker":"FERDINAND","text_entry":"Have I in such a prison."},{"line_id":92084,"play_name":"The Tempest","speech_number":130,"line_number":"1.2.582","speaker":"PROSPERO","text_entry":"[Aside]                It works."},{"line_id":92085,"play_name":"The Tempest","speech_number":130,"line_number":"1.2.0","speaker":"PROSPERO","text_entry":"To FERDINAND"},{"line_id":92086,"play_name":"The Tempest","speech_number":130,"line_number":"1.2.583","speaker":"PROSPERO","text_entry":"Come on."},{"line_id":92087,"play_name":"The Tempest","speech_number":130,"line_number":"1.2.584","speaker":"PROSPERO","text_entry":"Thou hast done well, fine Ariel!"},{"line_id":92088,"play_name":"The Tempest","speech_number":130,"line_number":"1.2.0","speaker":"PROSPERO","text_entry":"To FERDINAND"},{"line_id":92089,"play_name":"The Tempest","speech_number":130,"line_number":"1.2.585","speaker":"PROSPERO","text_entry":"Follow me."},{"line_id":92090,"play_name":"The Tempest","speech_number":130,"line_number":"1.2.0","speaker":"PROSPERO","text_entry":"To ARIEL"},{"line_id":92091,"play_name":"The Tempest","speech_number":130,"line_number":"1.2.586","speaker":"PROSPERO","text_entry":"Hark what thou else shalt do me."},{"line_id":92092,"play_name":"The Tempest","speech_number":131,"line_number":"1.2.587","speaker":"MIRANDA","text_entry":"Be of comfort;"},{"line_id":92093,"play_name":"The Tempest","speech_number":131,"line_number":"1.2.588","speaker":"MIRANDA","text_entry":"My father's of a better nature, sir,"},{"line_id":92094,"play_name":"The Tempest","speech_number":131,"line_number":"1.2.589","speaker":"MIRANDA","text_entry":"Than he appears by speech: this is unwonted"},{"line_id":92095,"play_name":"The Tempest","speech_number":131,"line_number":"1.2.590","speaker":"MIRANDA","text_entry":"Which now came from him."},{"line_id":92096,"play_name":"The Tempest","speech_number":132,"line_number":"1.2.591","speaker":"PROSPERO","text_entry":"Thou shalt be free"},{"line_id":92097,"play_name":"The Tempest","speech_number":132,"line_number":"1.2.592","speaker":"PROSPERO","text_entry":"As mountain winds: but then exactly do"},{"line_id":92098,"play_name":"The Tempest","speech_number":132,"line_number":"1.2.593","speaker":"PROSPERO","text_entry":"All points of my command."},{"line_id":92099,"play_name":"The Tempest","speech_number":133,"line_number":"1.2.594","speaker":"ARIEL","text_entry":"To the syllable."},{"line_id":92100,"play_name":"The Tempest","speech_number":134,"line_number":"1.2.595","speaker":"PROSPERO","text_entry":"Come, follow. Speak not for him."},{"line_id":92101,"play_name":"The Tempest","speech_number":134,"line_number":"1.2.0","speaker":"PROSPERO","text_entry":"Exeunt"}]