[{"line_id":43288,"play_name":"Henry VIII","speech_number":53,"line_number":"5.4.0","speaker":"KING HENRY VIII","text_entry":"SCENE IV. The palace yard."},{"line_id":43289,"play_name":"Henry VIII","speech_number":53,"line_number":"5.4.0","speaker":"KING HENRY VIII","text_entry":"Noise and tumult within. Enter Porter and his Man"},{"line_id":43290,"play_name":"Henry VIII","speech_number":1,"line_number":"5.4.1","speaker":"Porter","text_entry":"You'll leave your noise anon, ye rascals: do you"},{"line_id":43291,"play_name":"Henry VIII","speech_number":1,"line_number":"5.4.2","speaker":"Porter","text_entry":"take the court for Paris-garden? ye rude slaves,"},{"line_id":43292,"play_name":"Henry VIII","speech_number":1,"line_number":"5.4.3","speaker":"Porter","text_entry":"leave your gaping."},{"line_id":43293,"play_name":"Henry VIII","speech_number":1,"line_number":"5.4.0","speaker":"Porter","text_entry":"Within"},{"line_id":43294,"play_name":"Henry VIII","speech_number":1,"line_number":"5.4.4","speaker":"Porter","text_entry":"Good master porter, I belong to the larder."},{"line_id":43295,"play_name":"Henry VIII","speech_number":2,"line_number":"5.4.5","speaker":"Porter","text_entry":"Belong to the gallows, and be hanged, ye rogue! is"},{"line_id":43296,"play_name":"Henry VIII","speech_number":2,"line_number":"5.4.6","speaker":"Porter","text_entry":"this a place to roar in? Fetch me a dozen crab-tree"},{"line_id":43297,"play_name":"Henry VIII","speech_number":2,"line_number":"5.4.7","speaker":"Porter","text_entry":"staves, and strong ones: these are but switches to"},{"line_id":43298,"play_name":"Henry VIII","speech_number":2,"line_number":"5.4.8","speaker":"Porter","text_entry":"'em. I'll scratch your heads: you must be seeing"},{"line_id":43299,"play_name":"Henry VIII","speech_number":2,"line_number":"5.4.9","speaker":"Porter","text_entry":"christenings? do you look for ale and cakes here,"},{"line_id":43300,"play_name":"Henry VIII","speech_number":2,"line_number":"5.4.10","speaker":"Porter","text_entry":"you rude rascals?"},{"line_id":43301,"play_name":"Henry VIII","speech_number":3,"line_number":"5.4.11","speaker":"Man","text_entry":"Pray, sir, be patient: 'tis as much impossible--"},{"line_id":43302,"play_name":"Henry VIII","speech_number":3,"line_number":"5.4.12","speaker":"Man","text_entry":"Unless we sweep 'em from the door with cannons--"},{"line_id":43303,"play_name":"Henry VIII","speech_number":3,"line_number":"5.4.13","speaker":"Man","text_entry":"To scatter 'em, as 'tis to make 'em sleep"},{"line_id":43304,"play_name":"Henry VIII","speech_number":3,"line_number":"5.4.14","speaker":"Man","text_entry":"On May-day morning; which will never be:"},{"line_id":43305,"play_name":"Henry VIII","speech_number":3,"line_number":"5.4.15","speaker":"Man","text_entry":"We may as well push against Powle's, as stir em."},{"line_id":43306,"play_name":"Henry VIII","speech_number":4,"line_number":"5.4.16","speaker":"Porter","text_entry":"How got they in, and be hang'd?"},{"line_id":43307,"play_name":"Henry VIII","speech_number":5,"line_number":"5.4.17","speaker":"Man","text_entry":"Alas, I know not; how gets the tide in?"},{"line_id":43308,"play_name":"Henry VIII","speech_number":5,"line_number":"5.4.18","speaker":"Man","text_entry":"As much as one sound cudgel of four foot--"},{"line_id":43309,"play_name":"Henry VIII","speech_number":5,"line_number":"5.4.19","speaker":"Man","text_entry":"You see the poor remainder--could distribute,"},{"line_id":43310,"play_name":"Henry VIII","speech_number":5,"line_number":"5.4.20","speaker":"Man","text_entry":"I made no spare, sir."},{"line_id":43311,"play_name":"Henry VIII","speech_number":6,"line_number":"5.4.21","speaker":"Porter","text_entry":"You did nothing, sir."},{"line_id":43312,"play_name":"Henry VIII","speech_number":7,"line_number":"5.4.22","speaker":"Man","text_entry":"I am not Samson, nor Sir Guy, nor Colbrand,"},{"line_id":43313,"play_name":"Henry VIII","speech_number":7,"line_number":"5.4.23","speaker":"Man","text_entry":"To mow 'em down before me: but if I spared any"},{"line_id":43314,"play_name":"Henry VIII","speech_number":7,"line_number":"5.4.24","speaker":"Man","text_entry":"That had a head to hit, either young or old,"},{"line_id":43315,"play_name":"Henry VIII","speech_number":7,"line_number":"5.4.25","speaker":"Man","text_entry":"He or she, cuckold or cuckold-maker,"},{"line_id":43316,"play_name":"Henry VIII","speech_number":7,"line_number":"5.4.26","speaker":"Man","text_entry":"Let me ne'er hope to see a chine again"},{"line_id":43317,"play_name":"Henry VIII","speech_number":7,"line_number":"5.4.27","speaker":"Man","text_entry":"And that I would not for a cow, God save her!"},{"line_id":43318,"play_name":"Henry VIII","speech_number":7,"line_number":"5.4.0","speaker":"Man","text_entry":"Within"},{"line_id":43319,"play_name":"Henry VIII","speech_number":7,"line_number":"5.4.28","speaker":"Man","text_entry":"Do you hear, master porter?"},{"line_id":43320,"play_name":"Henry VIII","speech_number":8,"line_number":"5.4.29","speaker":"Porter","text_entry":"I shall be with you presently, good master puppy."},{"line_id":43321,"play_name":"Henry VIII","speech_number":8,"line_number":"5.4.30","speaker":"Porter","text_entry":"Keep the door close, sirrah."},{"line_id":43322,"play_name":"Henry VIII","speech_number":9,"line_number":"5.4.31","speaker":"Man","text_entry":"What would you have me do?"},{"line_id":43323,"play_name":"Henry VIII","speech_number":10,"line_number":"5.4.32","speaker":"Porter","text_entry":"What should you do, but knock 'em down by the"},{"line_id":43324,"play_name":"Henry VIII","speech_number":10,"line_number":"5.4.33","speaker":"Porter","text_entry":"dozens? Is this Moorfields to muster in? or have"},{"line_id":43325,"play_name":"Henry VIII","speech_number":10,"line_number":"5.4.34","speaker":"Porter","text_entry":"we some strange Indian with the great tool come to"},{"line_id":43326,"play_name":"Henry VIII","speech_number":10,"line_number":"5.4.35","speaker":"Porter","text_entry":"court, the women so besiege us? Bless me, what a"},{"line_id":43327,"play_name":"Henry VIII","speech_number":10,"line_number":"5.4.36","speaker":"Porter","text_entry":"fry of fornication is at door! On my Christian"},{"line_id":43328,"play_name":"Henry VIII","speech_number":10,"line_number":"5.4.37","speaker":"Porter","text_entry":"conscience, this one christening will beget a"},{"line_id":43329,"play_name":"Henry VIII","speech_number":10,"line_number":"5.4.38","speaker":"Porter","text_entry":"thousand; here will be father, godfather, and all together."},{"line_id":43330,"play_name":"Henry VIII","speech_number":11,"line_number":"5.4.39","speaker":"Man","text_entry":"The spoons will be the bigger, sir. There is a"},{"line_id":43331,"play_name":"Henry VIII","speech_number":11,"line_number":"5.4.40","speaker":"Man","text_entry":"fellow somewhat near the door, he should be a"},{"line_id":43332,"play_name":"Henry VIII","speech_number":11,"line_number":"5.4.41","speaker":"Man","text_entry":"brazier by his face, for, o' my conscience, twenty"},{"line_id":43333,"play_name":"Henry VIII","speech_number":11,"line_number":"5.4.42","speaker":"Man","text_entry":"of the dog-days now reign in's nose; all that stand"},{"line_id":43334,"play_name":"Henry VIII","speech_number":11,"line_number":"5.4.43","speaker":"Man","text_entry":"about him are under the line, they need no other"},{"line_id":43335,"play_name":"Henry VIII","speech_number":11,"line_number":"5.4.44","speaker":"Man","text_entry":"penance: that fire-drake did I hit three times on"},{"line_id":43336,"play_name":"Henry VIII","speech_number":11,"line_number":"5.4.45","speaker":"Man","text_entry":"the head, and three times was his nose discharged"},{"line_id":43337,"play_name":"Henry VIII","speech_number":11,"line_number":"5.4.46","speaker":"Man","text_entry":"against me; he stands there, like a mortar-piece, to"},{"line_id":43338,"play_name":"Henry VIII","speech_number":11,"line_number":"5.4.47","speaker":"Man","text_entry":"blow us. There was a haberdasher's wife of small"},{"line_id":43339,"play_name":"Henry VIII","speech_number":11,"line_number":"5.4.48","speaker":"Man","text_entry":"wit near him, that railed upon me till her pinked"},{"line_id":43340,"play_name":"Henry VIII","speech_number":11,"line_number":"5.4.49","speaker":"Man","text_entry":"porringer fell off her head, for kindling such a"},{"line_id":43341,"play_name":"Henry VIII","speech_number":11,"line_number":"5.4.50","speaker":"Man","text_entry":"combustion in the state. I missed the meteor once,"},{"line_id":43342,"play_name":"Henry VIII","speech_number":11,"line_number":"5.4.51","speaker":"Man","text_entry":"and hit that woman; who cried out 'Clubs!' when I"},{"line_id":43343,"play_name":"Henry VIII","speech_number":11,"line_number":"5.4.52","speaker":"Man","text_entry":"might see from far some forty truncheoners draw to"},{"line_id":43344,"play_name":"Henry VIII","speech_number":11,"line_number":"5.4.53","speaker":"Man","text_entry":"her succor, which were the hope o' the Strand, where"},{"line_id":43345,"play_name":"Henry VIII","speech_number":11,"line_number":"5.4.54","speaker":"Man","text_entry":"she was quartered. They fell on; I made good my"},{"line_id":43346,"play_name":"Henry VIII","speech_number":11,"line_number":"5.4.55","speaker":"Man","text_entry":"place: at length they came to the broom-staff to"},{"line_id":43347,"play_name":"Henry VIII","speech_number":11,"line_number":"5.4.56","speaker":"Man","text_entry":"me; I defied 'em still: when suddenly a file of"},{"line_id":43348,"play_name":"Henry VIII","speech_number":11,"line_number":"5.4.57","speaker":"Man","text_entry":"boys behind 'em, loose shot, delivered such a shower"},{"line_id":43349,"play_name":"Henry VIII","speech_number":11,"line_number":"5.4.58","speaker":"Man","text_entry":"of pebbles, that I was fain to draw mine honour in,"},{"line_id":43350,"play_name":"Henry VIII","speech_number":11,"line_number":"5.4.59","speaker":"Man","text_entry":"and let 'em win the work: the devil was amongst"},{"line_id":43351,"play_name":"Henry VIII","speech_number":11,"line_number":"5.4.60","speaker":"Man","text_entry":"'em, I think, surely."},{"line_id":43352,"play_name":"Henry VIII","speech_number":12,"line_number":"5.4.61","speaker":"Porter","text_entry":"These are the youths that thunder at a playhouse,"},{"line_id":43353,"play_name":"Henry VIII","speech_number":12,"line_number":"5.4.62","speaker":"Porter","text_entry":"and fight for bitten apples; that no audience, but"},{"line_id":43354,"play_name":"Henry VIII","speech_number":12,"line_number":"5.4.63","speaker":"Porter","text_entry":"the tribulation of Tower-hill, or the limbs of"},{"line_id":43355,"play_name":"Henry VIII","speech_number":12,"line_number":"5.4.64","speaker":"Porter","text_entry":"Limehouse, their dear brothers, are able to endure."},{"line_id":43356,"play_name":"Henry VIII","speech_number":12,"line_number":"5.4.65","speaker":"Porter","text_entry":"I have some of 'em in Limbo Patrum, and there they"},{"line_id":43357,"play_name":"Henry VIII","speech_number":12,"line_number":"5.4.66","speaker":"Porter","text_entry":"are like to dance these three days; besides the"},{"line_id":43358,"play_name":"Henry VIII","speech_number":12,"line_number":"5.4.67","speaker":"Porter","text_entry":"running banquet of two beadles that is to come."},{"line_id":43359,"play_name":"Henry VIII","speech_number":12,"line_number":"5.4.0","speaker":"Porter","text_entry":"Enter Chamberlain"},{"line_id":43360,"play_name":"Henry VIII","speech_number":13,"line_number":"5.4.68","speaker":"Chamberlain","text_entry":"Mercy o' me, what a multitude are here!"},{"line_id":43361,"play_name":"Henry VIII","speech_number":13,"line_number":"5.4.69","speaker":"Chamberlain","text_entry":"They grow still too; from all parts they are coming,"},{"line_id":43362,"play_name":"Henry VIII","speech_number":13,"line_number":"5.4.70","speaker":"Chamberlain","text_entry":"As if we kept a fair here! Where are these porters,"},{"line_id":43363,"play_name":"Henry VIII","speech_number":13,"line_number":"5.4.71","speaker":"Chamberlain","text_entry":"These lazy knaves? Ye have made a fine hand, fellows:"},{"line_id":43364,"play_name":"Henry VIII","speech_number":13,"line_number":"5.4.72","speaker":"Chamberlain","text_entry":"There's a trim rabble let in: are all these"},{"line_id":43365,"play_name":"Henry VIII","speech_number":13,"line_number":"5.4.73","speaker":"Chamberlain","text_entry":"Your faithful friends o' the suburbs? We shall have"},{"line_id":43366,"play_name":"Henry VIII","speech_number":13,"line_number":"5.4.74","speaker":"Chamberlain","text_entry":"Great store of room, no doubt, left for the ladies,"},{"line_id":43367,"play_name":"Henry VIII","speech_number":13,"line_number":"5.4.75","speaker":"Chamberlain","text_entry":"When they pass back from the christening."},{"line_id":43368,"play_name":"Henry VIII","speech_number":14,"line_number":"5.4.76","speaker":"Porter","text_entry":"An't please"},{"line_id":43369,"play_name":"Henry VIII","speech_number":14,"line_number":"5.4.77","speaker":"Porter","text_entry":"your honour,"},{"line_id":43370,"play_name":"Henry VIII","speech_number":14,"line_number":"5.4.78","speaker":"Porter","text_entry":"We are but men; and what so many may do,"},{"line_id":43371,"play_name":"Henry VIII","speech_number":14,"line_number":"5.4.79","speaker":"Porter","text_entry":"Not being torn a-pieces, we have done:"},{"line_id":43372,"play_name":"Henry VIII","speech_number":14,"line_number":"5.4.80","speaker":"Porter","text_entry":"An army cannot rule 'em."},{"line_id":43373,"play_name":"Henry VIII","speech_number":15,"line_number":"5.4.81","speaker":"Chamberlain","text_entry":"As I live,"},{"line_id":43374,"play_name":"Henry VIII","speech_number":15,"line_number":"5.4.82","speaker":"Chamberlain","text_entry":"If the king blame me for't, I'll lay ye all"},{"line_id":43375,"play_name":"Henry VIII","speech_number":15,"line_number":"5.4.83","speaker":"Chamberlain","text_entry":"By the heels, and suddenly; and on your heads"},{"line_id":43376,"play_name":"Henry VIII","speech_number":15,"line_number":"5.4.84","speaker":"Chamberlain","text_entry":"Clap round fines for neglect: ye are lazy knaves;"},{"line_id":43377,"play_name":"Henry VIII","speech_number":15,"line_number":"5.4.85","speaker":"Chamberlain","text_entry":"And here ye lie baiting of bombards, when"},{"line_id":43378,"play_name":"Henry VIII","speech_number":15,"line_number":"5.4.86","speaker":"Chamberlain","text_entry":"Ye should do service. Hark! the trumpets sound;"},{"line_id":43379,"play_name":"Henry VIII","speech_number":15,"line_number":"5.4.87","speaker":"Chamberlain","text_entry":"They're come already from the christening:"},{"line_id":43380,"play_name":"Henry VIII","speech_number":15,"line_number":"5.4.88","speaker":"Chamberlain","text_entry":"Go, break among the press, and find a way out"},{"line_id":43381,"play_name":"Henry VIII","speech_number":15,"line_number":"5.4.89","speaker":"Chamberlain","text_entry":"To let the troop pass fairly; or I'll find"},{"line_id":43382,"play_name":"Henry VIII","speech_number":15,"line_number":"5.4.90","speaker":"Chamberlain","text_entry":"A Marshalsea shall hold ye play these two months."},{"line_id":43383,"play_name":"Henry VIII","speech_number":16,"line_number":"5.4.91","speaker":"Porter","text_entry":"Make way there for the princess."},{"line_id":43384,"play_name":"Henry VIII","speech_number":17,"line_number":"5.4.92","speaker":"Man","text_entry":"You great fellow,"},{"line_id":43385,"play_name":"Henry VIII","speech_number":17,"line_number":"5.4.93","speaker":"Man","text_entry":"Stand close up, or I'll make your head ache."},{"line_id":43386,"play_name":"Henry VIII","speech_number":18,"line_number":"5.4.94","speaker":"Porter","text_entry":"You i' the camlet, get up o' the rail;"},{"line_id":43387,"play_name":"Henry VIII","speech_number":18,"line_number":"5.4.95","speaker":"Porter","text_entry":"I'll peck you o'er the pales else."},{"line_id":43388,"play_name":"Henry VIII","speech_number":18,"line_number":"5.4.0","speaker":"Porter","text_entry":"Exeunt"}]